[
    {
        "id_estacion":"9208E",
        "fecha":"2020-01-01",
        "precipitacion_maxima":"31.0(22)",
        "temperatura_media_minima_mensual":1.2,
        "temperatura_media_maxima_mensual":10.8,
        "temperatura_max_absoluta_mes":"16.3(05)",
        "temperatura_min_absoluta_mes":"-3.8(20)",
        "temperatura_minima_mas_baja":6.9,
        "tempetatura_mas_baja_mes":3.8,
        "dias_con_precipitacion_mayor_01":11.0,
        "dias_con_precipitacion_mayor_0100":9.0,
        "dias_con_precipitacion_mayor_10":3.0,
        "dias_con_precipitacion_mayor_30":1.0,
        "tension_vapor_media":58.0,
        "precipitacion_total_mes":81.2,
        "dias_temperatura_menor_0":10.0,
        "temperatura_media_mes":6.0,
        "indice_evaporacion":0.0959182687,
        "mes":1,
        "year":2020,
        "indice_solar":0.3,
        "sequia_meteorologica":0.0,
        "sequia_agricola":0.0,
        "nomb_estacion":"ARAGÜÉS DEL PUERTO",
        "provincia":"HUESCA",
        "lat":"424231N",
        "long":"004022W"
    },
    {
        "id_estacion":"9208E",
        "fecha":"2020-02-01",
        "precipitacion_maxima":"2.8(27)",
        "temperatura_media_minima_mensual":3.7,
        "temperatura_media_maxima_mensual":14.9,
        "temperatura_max_absoluta_mes":"20.1(24)",
        "temperatura_min_absoluta_mes":"-2.2(19)",
        "temperatura_minima_mas_baja":8.2,
        "tempetatura_mas_baja_mes":8.7,
        "dias_con_precipitacion_mayor_01":4.0,
        "dias_con_precipitacion_mayor_0100":3.0,
        "dias_con_precipitacion_mayor_10":0.0,
        "dias_con_precipitacion_mayor_30":0.0,
        "tension_vapor_media":64.0,
        "precipitacion_total_mes":6.2,
        "dias_temperatura_menor_0":3.0,
        "temperatura_media_mes":9.3,
        "indice_evaporacion":1.0,
        "mes":2,
        "year":2020,
        "indice_solar":0.4,
        "sequia_meteorologica":0.0,
        "sequia_agricola":0.0,
        "nomb_estacion":"ARAGÜÉS DEL PUERTO",
        "provincia":"HUESCA",
        "lat":"424231N",
        "long":"004022W"
    },
    {
        "id_estacion":"9208E",
        "fecha":"2020-03-01",
        "precipitacion_maxima":null,
        "temperatura_media_minima_mensual":null,
        "temperatura_media_maxima_mensual":null,
        "temperatura_max_absoluta_mes":null,
        "temperatura_min_absoluta_mes":null,
        "temperatura_minima_mas_baja":null,
        "tempetatura_mas_baja_mes":null,
        "dias_con_precipitacion_mayor_01":null,
        "dias_con_precipitacion_mayor_0100":null,
        "dias_con_precipitacion_mayor_10":null,
        "dias_con_precipitacion_mayor_30":null,
        "tension_vapor_media":null,
        "precipitacion_total_mes":null,
        "dias_temperatura_menor_0":null,
        "temperatura_media_mes":null,
        "indice_evaporacion":null,
        "mes":3,
        "year":2020,
        "indice_solar":0.5,
        "sequia_meteorologica":0.5,
        "sequia_agricola":0.5,
        "nomb_estacion":"ARAGÜÉS DEL PUERTO",
        "provincia":"HUESCA",
        "lat":"424231N",
        "long":"004022W"
    },
    {
        "id_estacion":"9208E",
        "fecha":"2020-04-01",
        "precipitacion_maxima":null,
        "temperatura_media_minima_mensual":null,
        "temperatura_media_maxima_mensual":null,
        "temperatura_max_absoluta_mes":null,
        "temperatura_min_absoluta_mes":null,
        "temperatura_minima_mas_baja":null,
        "tempetatura_mas_baja_mes":null,
        "dias_con_precipitacion_mayor_01":null,
        "dias_con_precipitacion_mayor_0100":null,
        "dias_con_precipitacion_mayor_10":null,
        "dias_con_precipitacion_mayor_30":null,
        "tension_vapor_media":null,
        "precipitacion_total_mes":null,
        "dias_temperatura_menor_0":null,
        "temperatura_media_mes":null,
        "indice_evaporacion":null,
        "mes":4,
        "year":2020,
        "indice_solar":0.6,
        "sequia_meteorologica":0.5,
        "sequia_agricola":0.5,
        "nomb_estacion":"ARAGÜÉS DEL PUERTO",
        "provincia":"HUESCA",
        "lat":"424231N",
        "long":"004022W"
    },
    {
        "id_estacion":"9208E",
        "fecha":"2020-05-01",
        "precipitacion_maxima":null,
        "temperatura_media_minima_mensual":null,
        "temperatura_media_maxima_mensual":null,
        "temperatura_max_absoluta_mes":null,
        "temperatura_min_absoluta_mes":null,
        "temperatura_minima_mas_baja":null,
        "tempetatura_mas_baja_mes":null,
        "dias_con_precipitacion_mayor_01":null,
        "dias_con_precipitacion_mayor_0100":null,
        "dias_con_precipitacion_mayor_10":null,
        "dias_con_precipitacion_mayor_30":null,
        "tension_vapor_media":null,
        "precipitacion_total_mes":null,
        "dias_temperatura_menor_0":null,
        "temperatura_media_mes":null,
        "indice_evaporacion":null,
        "mes":5,
        "year":2020,
        "indice_solar":0.7,
        "sequia_meteorologica":0.5,
        "sequia_agricola":0.5,
        "nomb_estacion":"ARAGÜÉS DEL PUERTO",
        "provincia":"HUESCA",
        "lat":"424231N",
        "long":"004022W"
    },
    {
        "id_estacion":"9208E",
        "fecha":"2020-06-01",
        "precipitacion_maxima":null,
        "temperatura_media_minima_mensual":10.6,
        "temperatura_media_maxima_mensual":21.9,
        "temperatura_max_absoluta_mes":"30.0(24)",
        "temperatura_min_absoluta_mes":"3.6(08)",
        "temperatura_minima_mas_baja":16.8,
        "tempetatura_mas_baja_mes":13.3,
        "dias_con_precipitacion_mayor_01":null,
        "dias_con_precipitacion_mayor_0100":null,
        "dias_con_precipitacion_mayor_10":null,
        "dias_con_precipitacion_mayor_30":null,
        "tension_vapor_media":117.0,
        "precipitacion_total_mes":null,
        "dias_temperatura_menor_0":0.0,
        "temperatura_media_mes":16.3,
        "indice_evaporacion":null,
        "mes":6,
        "year":2020,
        "indice_solar":0.9,
        "sequia_meteorologica":0.5,
        "sequia_agricola":0.5,
        "nomb_estacion":"ARAGÜÉS DEL PUERTO",
        "provincia":"HUESCA",
        "lat":"424231N",
        "long":"004022W"
    },
    {
        "id_estacion":"9208E",
        "fecha":"2020-07-01",
        "precipitacion_maxima":"19.0(12)",
        "temperatura_media_minima_mensual":14.5,
        "temperatura_media_maxima_mensual":29.7,
        "temperatura_max_absoluta_mes":"35.8(27)",
        "temperatura_min_absoluta_mes":"7.0(04)",
        "temperatura_minima_mas_baja":21.8,
        "tempetatura_mas_baja_mes":22.4,
        "dias_con_precipitacion_mayor_01":5.0,
        "dias_con_precipitacion_mayor_0100":3.0,
        "dias_con_precipitacion_mayor_10":1.0,
        "dias_con_precipitacion_mayor_30":0.0,
        "tension_vapor_media":121.0,
        "precipitacion_total_mes":27.4,
        "dias_temperatura_menor_0":0.0,
        "temperatura_media_mes":22.1,
        "indice_evaporacion":0.7386855105,
        "mes":7,
        "year":2020,
        "indice_solar":1.0,
        "sequia_meteorologica":0.0,
        "sequia_agricola":0.0,
        "nomb_estacion":"ARAGÜÉS DEL PUERTO",
        "provincia":"HUESCA",
        "lat":"424231N",
        "long":"004022W"
    },
    {
        "id_estacion":"9208E",
        "fecha":"2020-08-01",
        "precipitacion_maxima":"16.2(09)",
        "temperatura_media_minima_mensual":14.2,
        "temperatura_media_maxima_mensual":29.8,
        "temperatura_max_absoluta_mes":"37.7(07)",
        "temperatura_min_absoluta_mes":"5.7(31)",
        "temperatura_minima_mas_baja":20.0,
        "tempetatura_mas_baja_mes":19.1,
        "dias_con_precipitacion_mayor_01":9.0,
        "dias_con_precipitacion_mayor_0100":5.0,
        "dias_con_precipitacion_mayor_10":1.0,
        "dias_con_precipitacion_mayor_30":0.0,
        "tension_vapor_media":107.0,
        "precipitacion_total_mes":26.8,
        "dias_temperatura_menor_0":0.0,
        "temperatura_media_mes":22.0,
        "indice_evaporacion":0.7460976987,
        "mes":8,
        "year":2020,
        "indice_solar":0.9,
        "sequia_meteorologica":0.0,
        "sequia_agricola":0.0,
        "nomb_estacion":"ARAGÜÉS DEL PUERTO",
        "provincia":"HUESCA",
        "lat":"424231N",
        "long":"004022W"
    },
    {
        "id_estacion":"9208E",
        "fecha":"2020-09-01",
        "precipitacion_maxima":"35.4(18)",
        "temperatura_media_minima_mensual":11.3,
        "temperatura_media_maxima_mensual":23.7,
        "temperatura_max_absoluta_mes":"30.3(04)",
        "temperatura_min_absoluta_mes":"3.6(25)",
        "temperatura_minima_mas_baja":17.5,
        "tempetatura_mas_baja_mes":10.9,
        "dias_con_precipitacion_mayor_01":9.0,
        "dias_con_precipitacion_mayor_0100":7.0,
        "dias_con_precipitacion_mayor_10":4.0,
        "dias_con_precipitacion_mayor_30":2.0,
        "tension_vapor_media":97.0,
        "precipitacion_total_mes":107.4,
        "dias_temperatura_menor_0":0.0,
        "temperatura_media_mes":17.5,
        "indice_evaporacion":0.2172779369,
        "mes":9,
        "year":2020,
        "indice_solar":0.7,
        "sequia_meteorologica":0.019,
        "sequia_agricola":0.0101272206,
        "nomb_estacion":"ARAGÜÉS DEL PUERTO",
        "provincia":"HUESCA",
        "lat":"424231N",
        "long":"004022W"
    },
    {
        "id_estacion":"9208E",
        "fecha":"2020-10-01",
        "precipitacion_maxima":"39.0(02)",
        "temperatura_media_minima_mensual":5.8,
        "temperatura_media_maxima_mensual":14.9,
        "temperatura_max_absoluta_mes":"22.5(09)",
        "temperatura_min_absoluta_mes":"-0.2(16)",
        "temperatura_minima_mas_baja":11.7,
        "tempetatura_mas_baja_mes":6.5,
        "dias_con_precipitacion_mayor_01":17.0,
        "dias_con_precipitacion_mayor_0100":15.0,
        "dias_con_precipitacion_mayor_10":8.0,
        "dias_con_precipitacion_mayor_30":2.0,
        "tension_vapor_media":85.0,
        "precipitacion_total_mes":206.2,
        "dias_temperatura_menor_0":1.0,
        "temperatura_media_mes":10.4,
        "indice_evaporacion":0.0605296264,
        "mes":10,
        "year":2020,
        "indice_solar":0.5,
        "sequia_meteorologica":1.0,
        "sequia_agricola":1.0,
        "nomb_estacion":"ARAGÜÉS DEL PUERTO",
        "provincia":"HUESCA",
        "lat":"424231N",
        "long":"004022W"
    },
    {
        "id_estacion":"9208E",
        "fecha":"2020-11-01",
        "precipitacion_maxima":"39.2(07)",
        "temperatura_media_minima_mensual":5.7,
        "temperatura_media_maxima_mensual":15.3,
        "temperatura_max_absoluta_mes":"21.7(02)",
        "temperatura_min_absoluta_mes":"2.1(23)",
        "temperatura_minima_mas_baja":11.4,
        "tempetatura_mas_baja_mes":8.4,
        "dias_con_precipitacion_mayor_01":6.0,
        "dias_con_precipitacion_mayor_0100":5.0,
        "dias_con_precipitacion_mayor_10":1.0,
        "dias_con_precipitacion_mayor_30":1.0,
        "tension_vapor_media":78.0,
        "precipitacion_total_mes":63.6,
        "dias_temperatura_menor_0":0.0,
        "temperatura_media_mes":10.6,
        "indice_evaporacion":0.2219499648,
        "mes":11,
        "year":2020,
        "indice_solar":0.3,
        "sequia_meteorologica":0.0,
        "sequia_agricola":0.0,
        "nomb_estacion":"ARAGÜÉS DEL PUERTO",
        "provincia":"HUESCA",
        "lat":"424231N",
        "long":"004022W"
    },
    {
        "id_estacion":"9208E",
        "fecha":"2020-12-01",
        "precipitacion_maxima":"41.0(28)",
        "temperatura_media_minima_mensual":1.0,
        "temperatura_media_maxima_mensual":7.2,
        "temperatura_max_absoluta_mes":"16.9(22)",
        "temperatura_min_absoluta_mes":"-4.6(27)",
        "temperatura_minima_mas_baja":6.9,
        "tempetatura_mas_baja_mes":1.2,
        "dias_con_precipitacion_mayor_01":20.0,
        "dias_con_precipitacion_mayor_0100":18.0,
        "dias_con_precipitacion_mayor_10":12.0,
        "dias_con_precipitacion_mayor_30":3.0,
        "tension_vapor_media":62.0,
        "precipitacion_total_mes":325.2,
        "dias_temperatura_menor_0":15.0,
        "temperatura_media_mes":4.1,
        "indice_evaporacion":0.0,
        "mes":12,
        "year":2020,
        "indice_solar":0.2,
        "sequia_meteorologica":1.0,
        "sequia_agricola":1.0,
        "nomb_estacion":"ARAGÜÉS DEL PUERTO",
        "provincia":"HUESCA",
        "lat":"424231N",
        "long":"004022W"
    },
    {
        "id_estacion":"9208E",
        "fecha":"2021-01-01",
        "precipitacion_maxima":"34.4(23)",
        "temperatura_media_minima_mensual":-1.7,
        "temperatura_media_maxima_mensual":7.4,
        "temperatura_max_absoluta_mes":"16.8(28)",
        "temperatura_min_absoluta_mes":"-9.2(06)",
        "temperatura_minima_mas_baja":7.0,
        "tempetatura_mas_baja_mes":-1.1,
        "dias_con_precipitacion_mayor_01":17.0,
        "dias_con_precipitacion_mayor_0100":14.0,
        "dias_con_precipitacion_mayor_10":9.0,
        "dias_con_precipitacion_mayor_30":2.0,
        "tension_vapor_media":54.0,
        "precipitacion_total_mes":187.6,
        "dias_temperatura_menor_0":19.0,
        "temperatura_media_mes":2.9,
        "indice_evaporacion":0.0,
        "mes":1,
        "year":2021,
        "indice_solar":0.3,
        "sequia_meteorologica":0.8148333333,
        "sequia_agricola":0.8121333333,
        "nomb_estacion":"ARAGÜÉS DEL PUERTO",
        "provincia":"HUESCA",
        "lat":"424231N",
        "long":"004022W"
    },
    {
        "id_estacion":"9208E",
        "fecha":"2021-02-01",
        "precipitacion_maxima":"28.0(22)",
        "temperatura_media_minima_mensual":4.2,
        "temperatura_media_maxima_mensual":12.4,
        "temperatura_max_absoluta_mes":"18.0(20)",
        "temperatura_min_absoluta_mes":"-1.3(07)",
        "temperatura_minima_mas_baja":9.4,
        "tempetatura_mas_baja_mes":4.0,
        "dias_con_precipitacion_mayor_01":13.0,
        "dias_con_precipitacion_mayor_0100":12.0,
        "dias_con_precipitacion_mayor_10":5.0,
        "dias_con_precipitacion_mayor_30":0.0,
        "tension_vapor_media":70.0,
        "precipitacion_total_mes":120.6,
        "dias_temperatura_menor_0":1.0,
        "temperatura_media_mes":8.3,
        "indice_evaporacion":0.1134403053,
        "mes":2,
        "year":2021,
        "indice_solar":0.4,
        "sequia_meteorologica":0.1448333333,
        "sequia_agricola":0.1399989303,
        "nomb_estacion":"ARAGÜÉS DEL PUERTO",
        "provincia":"HUESCA",
        "lat":"424231N",
        "long":"004022W"
    },
    {
        "id_estacion":"9208E",
        "fecha":"2021-03-01",
        "precipitacion_maxima":"3.2(07)",
        "temperatura_media_minima_mensual":2.7,
        "temperatura_media_maxima_mensual":13.7,
        "temperatura_max_absoluta_mes":"21.9(31)",
        "temperatura_min_absoluta_mes":"-2.7(10)",
        "temperatura_minima_mas_baja":11.1,
        "tempetatura_mas_baja_mes":5.2,
        "dias_con_precipitacion_mayor_01":5.0,
        "dias_con_precipitacion_mayor_0100":4.0,
        "dias_con_precipitacion_mayor_10":0.0,
        "dias_con_precipitacion_mayor_30":0.0,
        "tension_vapor_media":56.0,
        "precipitacion_total_mes":10.2,
        "dias_temperatura_menor_0":5.0,
        "temperatura_media_mes":8.3,
        "indice_evaporacion":1.0,
        "mes":3,
        "year":2021,
        "indice_solar":0.5,
        "sequia_meteorologica":0.0,
        "sequia_agricola":0.0,
        "nomb_estacion":"ARAGÜÉS DEL PUERTO",
        "provincia":"HUESCA",
        "lat":"424231N",
        "long":"004022W"
    },
    {
        "id_estacion":"9208E",
        "fecha":"2021-04-01",
        "precipitacion_maxima":"29.2(20)",
        "temperatura_media_minima_mensual":4.0,
        "temperatura_media_maxima_mensual":14.9,
        "temperatura_max_absoluta_mes":"22.4(02)",
        "temperatura_min_absoluta_mes":"-3.6(07)",
        "temperatura_minima_mas_baja":10.2,
        "tempetatura_mas_baja_mes":7.8,
        "dias_con_precipitacion_mayor_01":14.0,
        "dias_con_precipitacion_mayor_0100":14.0,
        "dias_con_precipitacion_mayor_10":5.0,
        "dias_con_precipitacion_mayor_30":0.0,
        "tension_vapor_media":66.0,
        "precipitacion_total_mes":130.4,
        "dias_temperatura_menor_0":4.0,
        "temperatura_media_mes":9.5,
        "indice_evaporacion":0.1215493063,
        "mes":4,
        "year":2021,
        "indice_solar":0.6,
        "sequia_meteorologica":0.2428333333,
        "sequia_agricola":0.2359178403,
        "nomb_estacion":"ARAGÜÉS DEL PUERTO",
        "provincia":"HUESCA",
        "lat":"424231N",
        "long":"004022W"
    },
    {
        "id_estacion":"9208E",
        "fecha":"2021-05-01",
        "precipitacion_maxima":"34.8(09)",
        "temperatura_media_minima_mensual":6.7,
        "temperatura_media_maxima_mensual":18.2,
        "temperatura_max_absoluta_mes":"26.9(31)",
        "temperatura_min_absoluta_mes":"-0.3(02)",
        "temperatura_minima_mas_baja":13.7,
        "tempetatura_mas_baja_mes":11.4,
        "dias_con_precipitacion_mayor_01":12.0,
        "dias_con_precipitacion_mayor_0100":6.0,
        "dias_con_precipitacion_mayor_10":1.0,
        "dias_con_precipitacion_mayor_30":1.0,
        "tension_vapor_media":87.0,
        "precipitacion_total_mes":59.0,
        "dias_temperatura_menor_0":1.0,
        "temperatura_media_mes":12.4,
        "indice_evaporacion":0.3655678235,
        "mes":5,
        "year":2021,
        "indice_solar":0.7,
        "sequia_meteorologica":0.0,
        "sequia_agricola":0.0,
        "nomb_estacion":"ARAGÜÉS DEL PUERTO",
        "provincia":"HUESCA",
        "lat":"424231N",
        "long":"004022W"
    },
    {
        "id_estacion":"9208E",
        "fecha":"2021-06-01",
        "precipitacion_maxima":"22.2(17)",
        "temperatura_media_minima_mensual":12.0,
        "temperatura_media_maxima_mensual":24.1,
        "temperatura_max_absoluta_mes":"31.5(14)",
        "temperatura_min_absoluta_mes":"6.4(24)",
        "temperatura_minima_mas_baja":19.0,
        "tempetatura_mas_baja_mes":16.7,
        "dias_con_precipitacion_mayor_01":8.0,
        "dias_con_precipitacion_mayor_0100":7.0,
        "dias_con_precipitacion_mayor_10":2.0,
        "dias_con_precipitacion_mayor_30":0.0,
        "tension_vapor_media":115.0,
        "precipitacion_total_mes":65.6,
        "dias_temperatura_menor_0":0.0,
        "temperatura_media_mes":18.1,
        "indice_evaporacion":0.4638062888,
        "mes":6,
        "year":2021,
        "indice_solar":0.9,
        "sequia_meteorologica":0.0,
        "sequia_agricola":0.0,
        "nomb_estacion":"ARAGÜÉS DEL PUERTO",
        "provincia":"HUESCA",
        "lat":"424231N",
        "long":"004022W"
    },
    {
        "id_estacion":"9208E",
        "fecha":"2021-07-01",
        "precipitacion_maxima":"12.6(29)",
        "temperatura_media_minima_mensual":14.0,
        "temperatura_media_maxima_mensual":27.2,
        "temperatura_max_absoluta_mes":"34.2(22)",
        "temperatura_min_absoluta_mes":"7.5(08)",
        "temperatura_minima_mas_baja":21.4,
        "tempetatura_mas_baja_mes":16.8,
        "dias_con_precipitacion_mayor_01":4.0,
        "dias_con_precipitacion_mayor_0100":3.0,
        "dias_con_precipitacion_mayor_10":1.0,
        "dias_con_precipitacion_mayor_30":0.0,
        "tension_vapor_media":113.0,
        "precipitacion_total_mes":31.0,
        "dias_temperatura_menor_0":0.0,
        "temperatura_media_mes":20.6,
        "indice_evaporacion":0.8859695634,
        "mes":7,
        "year":2021,
        "indice_solar":1.0,
        "sequia_meteorologica":0.0,
        "sequia_agricola":0.0,
        "nomb_estacion":"ARAGÜÉS DEL PUERTO",
        "provincia":"HUESCA",
        "lat":"424231N",
        "long":"004022W"
    },
    {
        "id_estacion":"9208E",
        "fecha":"2021-08-01",
        "precipitacion_maxima":"7.6(03)",
        "temperatura_media_minima_mensual":13.6,
        "temperatura_media_maxima_mensual":29.0,
        "temperatura_max_absoluta_mes":"37.6(14)",
        "temperatura_min_absoluta_mes":"8.0(01)",
        "temperatura_minima_mas_baja":23.9,
        "tempetatura_mas_baja_mes":21.7,
        "dias_con_precipitacion_mayor_01":6.0,
        "dias_con_precipitacion_mayor_0100":4.0,
        "dias_con_precipitacion_mayor_10":0.0,
        "dias_con_precipitacion_mayor_30":0.0,
        "tension_vapor_media":105.0,
        "precipitacion_total_mes":27.4,
        "dias_temperatura_menor_0":0.0,
        "temperatura_media_mes":21.4,
        "indice_evaporacion":0.9766420982,
        "mes":8,
        "year":2021,
        "indice_solar":0.9,
        "sequia_meteorologica":0.0,
        "sequia_agricola":0.0,
        "nomb_estacion":"ARAGÜÉS DEL PUERTO",
        "provincia":"HUESCA",
        "lat":"424231N",
        "long":"004022W"
    },
    {
        "id_estacion":"9208E",
        "fecha":"2021-09-01",
        "precipitacion_maxima":"25.2(01)",
        "temperatura_media_minima_mensual":12.5,
        "temperatura_media_maxima_mensual":22.9,
        "temperatura_max_absoluta_mes":"31.0(06)",
        "temperatura_min_absoluta_mes":"4.8(21)",
        "temperatura_minima_mas_baja":20.3,
        "tempetatura_mas_baja_mes":15.4,
        "dias_con_precipitacion_mayor_01":13.0,
        "dias_con_precipitacion_mayor_0100":10.0,
        "dias_con_precipitacion_mayor_10":6.0,
        "dias_con_precipitacion_mayor_30":0.0,
        "tension_vapor_media":120.0,
        "precipitacion_total_mes":123.4,
        "dias_temperatura_menor_0":0.0,
        "temperatura_media_mes":17.8,
        "indice_evaporacion":0.2557285308,
        "mes":9,
        "year":2021,
        "indice_solar":0.7,
        "sequia_meteorologica":0.1728333333,
        "sequia_agricola":0.163576048,
        "nomb_estacion":"ARAGÜÉS DEL PUERTO",
        "provincia":"HUESCA",
        "lat":"424231N",
        "long":"004022W"
    },
    {
        "id_estacion":"9208E",
        "fecha":"2021-10-01",
        "precipitacion_maxima":"49.0(03)",
        "temperatura_media_minima_mensual":7.2,
        "temperatura_media_maxima_mensual":19.2,
        "temperatura_max_absoluta_mes":"22.9(07)",
        "temperatura_min_absoluta_mes":"1.8(23)",
        "temperatura_minima_mas_baja":13.4,
        "tempetatura_mas_baja_mes":11.6,
        "dias_con_precipitacion_mayor_01":7.0,
        "dias_con_precipitacion_mayor_0100":7.0,
        "dias_con_precipitacion_mayor_10":3.0,
        "dias_con_precipitacion_mayor_30":2.0,
        "tension_vapor_media":86.0,
        "precipitacion_total_mes":127.2,
        "dias_temperatura_menor_0":0.0,
        "temperatura_media_mes":13.2,
        "indice_evaporacion":0.1817937006,
        "mes":10,
        "year":2021,
        "indice_solar":0.5,
        "sequia_meteorologica":0.2108333333,
        "sequia_agricola":0.2043153963,
        "nomb_estacion":"ARAGÜÉS DEL PUERTO",
        "provincia":"HUESCA",
        "lat":"424231N",
        "long":"004022W"
    },
    {
        "id_estacion":"9208E",
        "fecha":"2021-11-01",
        "precipitacion_maxima":"35.0(23)",
        "temperatura_media_minima_mensual":1.8,
        "temperatura_media_maxima_mensual":11.2,
        "temperatura_max_absoluta_mes":"18.2(12)",
        "temperatura_min_absoluta_mes":"-1.7(28)",
        "temperatura_minima_mas_baja":5.8,
        "tempetatura_mas_baja_mes":1.5,
        "dias_con_precipitacion_mayor_01":10.0,
        "dias_con_precipitacion_mayor_0100":8.0,
        "dias_con_precipitacion_mayor_10":4.0,
        "dias_con_precipitacion_mayor_30":2.0,
        "tension_vapor_media":60.0,
        "precipitacion_total_mes":121.4,
        "dias_temperatura_menor_0":7.0,
        "temperatura_media_mes":6.5,
        "indice_evaporacion":0.0821314602,
        "mes":11,
        "year":2021,
        "indice_solar":0.3,
        "sequia_meteorologica":0.1528333333,
        "sequia_agricola":0.1493120187,
        "nomb_estacion":"ARAGÜÉS DEL PUERTO",
        "provincia":"HUESCA",
        "lat":"424231N",
        "long":"004022W"
    },
    {
        "id_estacion":"9208E",
        "fecha":"2021-12-01",
        "precipitacion_maxima":"110.8(09)",
        "temperatura_media_minima_mensual":3.1,
        "temperatura_media_maxima_mensual":11.2,
        "temperatura_max_absoluta_mes":"20.9(31)",
        "temperatura_min_absoluta_mes":"-1.1(09)",
        "temperatura_minima_mas_baja":9.0,
        "tempetatura_mas_baja_mes":1.5,
        "dias_con_precipitacion_mayor_01":15.0,
        "dias_con_precipitacion_mayor_0100":12.0,
        "dias_con_precipitacion_mayor_10":6.0,
        "dias_con_precipitacion_mayor_30":3.0,
        "tension_vapor_media":67.0,
        "precipitacion_total_mes":269.6,
        "dias_temperatura_menor_0":5.0,
        "temperatura_media_mes":7.2,
        "indice_evaporacion":0.0248911709,
        "mes":12,
        "year":2021,
        "indice_solar":0.2,
        "sequia_meteorologica":1.0,
        "sequia_agricola":1.0,
        "nomb_estacion":"ARAGÜÉS DEL PUERTO",
        "provincia":"HUESCA",
        "lat":"424231N",
        "long":"004022W"
    },
    {
        "id_estacion":"9208E",
        "fecha":"2022-01-01",
        "precipitacion_maxima":"53.2(09)",
        "temperatura_media_minima_mensual":0.5,
        "temperatura_media_maxima_mensual":12.1,
        "temperatura_max_absoluta_mes":"19.7(01)",
        "temperatura_min_absoluta_mes":"-5.5(06)",
        "temperatura_minima_mas_baja":9.9,
        "tempetatura_mas_baja_mes":5.0,
        "dias_con_precipitacion_mayor_01":4.0,
        "dias_con_precipitacion_mayor_0100":4.0,
        "dias_con_precipitacion_mayor_10":2.0,
        "dias_con_precipitacion_mayor_30":1.0,
        "tension_vapor_media":41.0,
        "precipitacion_total_mes":82.8,
        "dias_temperatura_menor_0":16.0,
        "temperatura_media_mes":6.3,
        "indice_evaporacion":0.0604524686,
        "mes":1,
        "year":2022,
        "indice_solar":0.3,
        "sequia_meteorologica":0.0618333333,
        "sequia_agricola":0.0585288086,
        "nomb_estacion":"ARAGÜÉS DEL PUERTO",
        "provincia":"HUESCA",
        "lat":"424231N",
        "long":"004022W"
    },
    {
        "id_estacion":"9208E",
        "fecha":"2022-02-01",
        "precipitacion_maxima":"12.8(13)",
        "temperatura_media_minima_mensual":2.0,
        "temperatura_media_maxima_mensual":13.8,
        "temperatura_max_absoluta_mes":"20.5(02)",
        "temperatura_min_absoluta_mes":"-2.3(06)",
        "temperatura_minima_mas_baja":6.2,
        "tempetatura_mas_baja_mes":6.7,
        "dias_con_precipitacion_mayor_01":2.0,
        "dias_con_precipitacion_mayor_0100":2.0,
        "dias_con_precipitacion_mayor_10":1.0,
        "dias_con_precipitacion_mayor_30":0.0,
        "tension_vapor_media":55.0,
        "precipitacion_total_mes":21.8,
        "dias_temperatura_menor_0":5.0,
        "temperatura_media_mes":7.9,
        "indice_evaporacion":0.5144402468,
        "mes":2,
        "year":2022,
        "indice_solar":0.4,
        "sequia_meteorologica":0.0,
        "sequia_agricola":0.0,
        "nomb_estacion":"ARAGÜÉS DEL PUERTO",
        "provincia":"HUESCA",
        "lat":"424231N",
        "long":"004022W"
    },
    {
        "id_estacion":"9208E",
        "fecha":"2022-03-01",
        "precipitacion_maxima":"25.0(11)",
        "temperatura_media_minima_mensual":3.3,
        "temperatura_media_maxima_mensual":11.8,
        "temperatura_max_absoluta_mes":"18.8(15)",
        "temperatura_min_absoluta_mes":"-1.2(07)",
        "temperatura_minima_mas_baja":12.9,
        "tempetatura_mas_baja_mes":5.2,
        "dias_con_precipitacion_mayor_01":14.0,
        "dias_con_precipitacion_mayor_0100":12.0,
        "dias_con_precipitacion_mayor_10":3.0,
        "dias_con_precipitacion_mayor_30":0.0,
        "tension_vapor_media":64.0,
        "precipitacion_total_mes":72.4,
        "dias_temperatura_menor_0":4.0,
        "temperatura_media_mes":7.6,
        "indice_evaporacion":0.1169269972,
        "mes":3,
        "year":2022,
        "indice_solar":0.5,
        "sequia_meteorologica":0.0,
        "sequia_agricola":0.0,
        "nomb_estacion":"ARAGÜÉS DEL PUERTO",
        "provincia":"HUESCA",
        "lat":"424231N",
        "long":"004022W"
    },
    {
        "id_estacion":"9208E",
        "fecha":"2022-04-01",
        "precipitacion_maxima":"40.2(23)",
        "temperatura_media_minima_mensual":3.7,
        "temperatura_media_maxima_mensual":15.1,
        "temperatura_max_absoluta_mes":"23.4(16)",
        "temperatura_min_absoluta_mes":"-5.5(04)",
        "temperatura_minima_mas_baja":9.7,
        "tempetatura_mas_baja_mes":2.7,
        "dias_con_precipitacion_mayor_01":12.0,
        "dias_con_precipitacion_mayor_0100":8.0,
        "dias_con_precipitacion_mayor_10":4.0,
        "dias_con_precipitacion_mayor_30":1.0,
        "tension_vapor_media":71.0,
        "precipitacion_total_mes":137.2,
        "dias_temperatura_menor_0":5.0,
        "temperatura_media_mes":9.4,
        "indice_evaporacion":0.045139433,
        "mes":4,
        "year":2022,
        "indice_solar":0.6,
        "sequia_meteorologica":0.6058333333,
        "sequia_agricola":0.599681939,
        "nomb_estacion":"ARAGÜÉS DEL PUERTO",
        "provincia":"HUESCA",
        "lat":"424231N",
        "long":"004022W"
    },
    {
        "id_estacion":"9208E",
        "fecha":"2022-05-01",
        "precipitacion_maxima":"7.0(02)",
        "temperatura_media_minima_mensual":11.0,
        "temperatura_media_maxima_mensual":23.0,
        "temperatura_max_absoluta_mes":"32.4(21)",
        "temperatura_min_absoluta_mes":"4.8(05)",
        "temperatura_minima_mas_baja":19.0,
        "tempetatura_mas_baja_mes":12.2,
        "dias_con_precipitacion_mayor_01":7.0,
        "dias_con_precipitacion_mayor_0100":5.0,
        "dias_con_precipitacion_mayor_10":0.0,
        "dias_con_precipitacion_mayor_30":0.0,
        "tension_vapor_media":87.0,
        "precipitacion_total_mes":18.8,
        "dias_temperatura_menor_0":0.0,
        "temperatura_media_mes":17.0,
        "indice_evaporacion":1.0,
        "mes":5,
        "year":2022,
        "indice_solar":0.7,
        "sequia_meteorologica":0.0,
        "sequia_agricola":0.0,
        "nomb_estacion":"ARAGÜÉS DEL PUERTO",
        "provincia":"HUESCA",
        "lat":"424231N",
        "long":"004022W"
    },
    {
        "id_estacion":"9208E",
        "fecha":"2022-06-01",
        "precipitacion_maxima":"13.4(21)",
        "temperatura_media_minima_mensual":14.9,
        "temperatura_media_maxima_mensual":27.9,
        "temperatura_max_absoluta_mes":"36.2(17)",
        "temperatura_min_absoluta_mes":"8.6(30)",
        "temperatura_minima_mas_baja":23.1,
        "tempetatura_mas_baja_mes":21.4,
        "dias_con_precipitacion_mayor_01":8.0,
        "dias_con_precipitacion_mayor_0100":5.0,
        "dias_con_precipitacion_mayor_10":1.0,
        "dias_con_precipitacion_mayor_30":0.0,
        "tension_vapor_media":106.0,
        "precipitacion_total_mes":26.2,
        "dias_temperatura_menor_0":0.0,
        "temperatura_media_mes":21.4,
        "indice_evaporacion":0.9412297067,
        "mes":6,
        "year":2022,
        "indice_solar":0.9,
        "sequia_meteorologica":0.0,
        "sequia_agricola":0.0,
        "nomb_estacion":"ARAGÜÉS DEL PUERTO",
        "provincia":"HUESCA",
        "lat":"424231N",
        "long":"004022W"
    },
    {
        "id_estacion":"9208E",
        "fecha":"2022-07-01",
        "precipitacion_maxima":"16.4(19)",
        "temperatura_media_minima_mensual":16.2,
        "temperatura_media_maxima_mensual":31.9,
        "temperatura_max_absoluta_mes":"37.8(17)",
        "temperatura_min_absoluta_mes":"6.4(01)",
        "temperatura_minima_mas_baja":23.1,
        "tempetatura_mas_baja_mes":19.8,
        "dias_con_precipitacion_mayor_01":6.0,
        "dias_con_precipitacion_mayor_0100":6.0,
        "dias_con_precipitacion_mayor_10":1.0,
        "dias_con_precipitacion_mayor_30":0.0,
        "tension_vapor_media":113.0,
        "precipitacion_total_mes":50.4,
        "dias_temperatura_menor_0":0.0,
        "temperatura_media_mes":24.1,
        "indice_evaporacion":0.6481046663,
        "mes":7,
        "year":2022,
        "indice_solar":1.0,
        "sequia_meteorologica":0.0,
        "sequia_agricola":0.0,
        "nomb_estacion":"ARAGÜÉS DEL PUERTO",
        "provincia":"HUESCA",
        "lat":"424231N",
        "long":"004022W"
    },
    {
        "id_estacion":"9208E",
        "fecha":"2022-08-01",
        "precipitacion_maxima":"37.0(29)",
        "temperatura_media_minima_mensual":16.1,
        "temperatura_media_maxima_mensual":31.0,
        "temperatura_max_absoluta_mes":"35.6(12)",
        "temperatura_min_absoluta_mes":"10.0(19)",
        "temperatura_minima_mas_baja":21.9,
        "tempetatura_mas_baja_mes":20.9,
        "dias_con_precipitacion_mayor_01":8.0,
        "dias_con_precipitacion_mayor_0100":6.0,
        "dias_con_precipitacion_mayor_10":1.0,
        "dias_con_precipitacion_mayor_30":1.0,
        "tension_vapor_media":115.0,
        "precipitacion_total_mes":55.4,
        "dias_temperatura_menor_0":0.0,
        "temperatura_media_mes":23.5,
        "indice_evaporacion":0.5884879656,
        "mes":8,
        "year":2022,
        "indice_solar":0.9,
        "sequia_meteorologica":0.0,
        "sequia_agricola":0.0,
        "nomb_estacion":"ARAGÜÉS DEL PUERTO",
        "provincia":"HUESCA",
        "lat":"424231N",
        "long":"004022W"
    },
    {
        "id_estacion":"9208E",
        "fecha":"2022-09-01",
        "precipitacion_maxima":"19.4(12)",
        "temperatura_media_minima_mensual":11.5,
        "temperatura_media_maxima_mensual":23.4,
        "temperatura_max_absoluta_mes":"31.8(11)",
        "temperatura_min_absoluta_mes":"4.1(30)",
        "temperatura_minima_mas_baja":17.1,
        "tempetatura_mas_baja_mes":12.0,
        "dias_con_precipitacion_mayor_01":12.0,
        "dias_con_precipitacion_mayor_0100":10.0,
        "dias_con_precipitacion_mayor_10":2.0,
        "dias_con_precipitacion_mayor_30":0.0,
        "tension_vapor_media":102.0,
        "precipitacion_total_mes":74.8,
        "dias_temperatura_menor_0":0.0,
        "temperatura_media_mes":17.5,
        "indice_evaporacion":0.3368445612,
        "mes":9,
        "year":2022,
        "indice_solar":0.7,
        "sequia_meteorologica":0.0,
        "sequia_agricola":0.0,
        "nomb_estacion":"ARAGÜÉS DEL PUERTO",
        "provincia":"HUESCA",
        "lat":"424231N",
        "long":"004022W"
    },
    {
        "id_estacion":"9208E",
        "fecha":"2022-10-01",
        "precipitacion_maxima":"21.6(19)",
        "temperatura_media_minima_mensual":12.3,
        "temperatura_media_maxima_mensual":22.0,
        "temperatura_max_absoluta_mes":"26.9(03)",
        "temperatura_min_absoluta_mes":"5.5(01)",
        "temperatura_minima_mas_baja":16.6,
        "tempetatura_mas_baja_mes":15.3,
        "dias_con_precipitacion_mayor_01":13.0,
        "dias_con_precipitacion_mayor_0100":9.0,
        "dias_con_precipitacion_mayor_10":3.0,
        "dias_con_precipitacion_mayor_30":0.0,
        "tension_vapor_media":98.0,
        "precipitacion_total_mes":65.2,
        "dias_temperatura_menor_0":0.0,
        "temperatura_media_mes":17.2,
        "indice_evaporacion":0.3813369603,
        "mes":10,
        "year":2022,
        "indice_solar":0.5,
        "sequia_meteorologica":0.0,
        "sequia_agricola":0.0,
        "nomb_estacion":"ARAGÜÉS DEL PUERTO",
        "provincia":"HUESCA",
        "lat":"424231N",
        "long":"004022W"
    },
    {
        "id_estacion":"9208E",
        "fecha":"2022-11-01",
        "precipitacion_maxima":"34.6(22)",
        "temperatura_media_minima_mensual":4.6,
        "temperatura_media_maxima_mensual":13.1,
        "temperatura_max_absoluta_mes":"19.0(13)",
        "temperatura_min_absoluta_mes":"0.1(20)",
        "temperatura_minima_mas_baja":10.9,
        "tempetatura_mas_baja_mes":4.4,
        "dias_con_precipitacion_mayor_01":19.0,
        "dias_con_precipitacion_mayor_0100":17.0,
        "dias_con_precipitacion_mayor_10":6.0,
        "dias_con_precipitacion_mayor_30":2.0,
        "tension_vapor_media":77.0,
        "precipitacion_total_mes":158.4,
        "dias_temperatura_menor_0":0.0,
        "temperatura_media_mes":8.9,
        "indice_evaporacion":0.0197482386,
        "mes":11,
        "year":2022,
        "indice_solar":0.3,
        "sequia_meteorologica":0.8178333333,
        "sequia_agricola":0.8149358509,
        "nomb_estacion":"ARAGÜÉS DEL PUERTO",
        "provincia":"HUESCA",
        "lat":"424231N",
        "long":"004022W"
    },
    {
        "id_estacion":"9208E",
        "fecha":"2022-12-01",
        "precipitacion_maxima":"31.0(12)",
        "temperatura_media_minima_mensual":3.8,
        "temperatura_media_maxima_mensual":10.8,
        "temperatura_max_absoluta_mes":"17.4(24)",
        "temperatura_min_absoluta_mes":"-4.3(10)",
        "temperatura_minima_mas_baja":8.2,
        "tempetatura_mas_baja_mes":1.6,
        "dias_con_precipitacion_mayor_01":16.0,
        "dias_con_precipitacion_mayor_0100":12.0,
        "dias_con_precipitacion_mayor_10":5.0,
        "dias_con_precipitacion_mayor_30":2.0,
        "tension_vapor_media":75.0,
        "precipitacion_total_mes":156.0,
        "dias_temperatura_menor_0":8.0,
        "temperatura_media_mes":7.3,
        "indice_evaporacion":0.0,
        "mes":12,
        "year":2022,
        "indice_solar":0.2,
        "sequia_meteorologica":0.7938333333,
        "sequia_agricola":0.7921333333,
        "nomb_estacion":"ARAGÜÉS DEL PUERTO",
        "provincia":"HUESCA",
        "lat":"424231N",
        "long":"004022W"
    },
    {
        "id_estacion":"9208E",
        "fecha":"2023-01-01",
        "precipitacion_maxima":"70.6(16)",
        "temperatura_media_minima_mensual":-1.4,
        "temperatura_media_maxima_mensual":7.9,
        "temperatura_max_absoluta_mes":"15.9(01)",
        "temperatura_min_absoluta_mes":"-9.3(24)",
        "temperatura_minima_mas_baja":9.4,
        "tempetatura_mas_baja_mes":1.7,
        "dias_con_precipitacion_mayor_01":12.0,
        "dias_con_precipitacion_mayor_0100":9.0,
        "dias_con_precipitacion_mayor_10":6.0,
        "dias_con_precipitacion_mayor_30":1.0,
        "tension_vapor_media":49.0,
        "precipitacion_total_mes":196.8,
        "dias_temperatura_menor_0":18.0,
        "temperatura_media_mes":3.3,
        "indice_evaporacion":0.0,
        "mes":1,
        "year":2023,
        "indice_solar":0.3,
        "sequia_meteorologica":0.8013333333,
        "sequia_agricola":0.7986333333,
        "nomb_estacion":"ARAGÜÉS DEL PUERTO",
        "provincia":"HUESCA",
        "lat":"424231N",
        "long":"004022W"
    },
    {
        "id_estacion":"9208E",
        "fecha":"2023-02-01",
        "precipitacion_maxima":"27.4(23)",
        "temperatura_media_minima_mensual":-0.1,
        "temperatura_media_maxima_mensual":11.4,
        "temperatura_max_absoluta_mes":"20.2(20)",
        "temperatura_min_absoluta_mes":"-6.9(28)",
        "temperatura_minima_mas_baja":7.0,
        "tempetatura_mas_baja_mes":0.6,
        "dias_con_precipitacion_mayor_01":4.0,
        "dias_con_precipitacion_mayor_0100":3.0,
        "dias_con_precipitacion_mayor_10":2.0,
        "dias_con_precipitacion_mayor_30":0.0,
        "tension_vapor_media":42.0,
        "precipitacion_total_mes":42.4,
        "dias_temperatura_menor_0":15.0,
        "temperatura_media_mes":5.7,
        "indice_evaporacion":0.1802376794,
        "mes":2,
        "year":2023,
        "indice_solar":0.4,
        "sequia_meteorologica":0.0,
        "sequia_agricola":0.0,
        "nomb_estacion":"ARAGÜÉS DEL PUERTO",
        "provincia":"HUESCA",
        "lat":"424231N",
        "long":"004022W"
    },
    {
        "id_estacion":"9208E",
        "fecha":"2023-03-01",
        "precipitacion_maxima":"12.4(08)",
        "temperatura_media_minima_mensual":4.0,
        "temperatura_media_maxima_mensual":15.2,
        "temperatura_max_absoluta_mes":"23.0(29)",
        "temperatura_min_absoluta_mes":"-8.0(01)",
        "temperatura_minima_mas_baja":10.9,
        "tempetatura_mas_baja_mes":4.3,
        "dias_con_precipitacion_mayor_01":13.0,
        "dias_con_precipitacion_mayor_0100":8.0,
        "dias_con_precipitacion_mayor_10":1.0,
        "dias_con_precipitacion_mayor_30":0.0,
        "tension_vapor_media":65.0,
        "precipitacion_total_mes":28.0,
        "dias_temperatura_menor_0":6.0,
        "temperatura_media_mes":9.6,
        "indice_evaporacion":0.4219695879,
        "mes":3,
        "year":2023,
        "indice_solar":0.5,
        "sequia_meteorologica":0.0,
        "sequia_agricola":0.0,
        "nomb_estacion":"ARAGÜÉS DEL PUERTO",
        "provincia":"HUESCA",
        "lat":"424231N",
        "long":"004022W"
    },
    {
        "id_estacion":"9208E",
        "fecha":"2023-04-01",
        "precipitacion_maxima":"22.4(22)",
        "temperatura_media_minima_mensual":5.8,
        "temperatura_media_maxima_mensual":17.6,
        "temperatura_max_absoluta_mes":"26.2(28)",
        "temperatura_min_absoluta_mes":"-0.2(05)",
        "temperatura_minima_mas_baja":15.3,
        "tempetatura_mas_baja_mes":5.1,
        "dias_con_precipitacion_mayor_01":8.0,
        "dias_con_precipitacion_mayor_0100":8.0,
        "dias_con_precipitacion_mayor_10":2.0,
        "dias_con_precipitacion_mayor_30":0.0,
        "tension_vapor_media":68.0,
        "precipitacion_total_mes":63.2,
        "dias_temperatura_menor_0":1.0,
        "temperatura_media_mes":11.7,
        "indice_evaporacion":0.2468566557,
        "mes":4,
        "year":2023,
        "indice_solar":0.6,
        "sequia_meteorologica":0.0,
        "sequia_agricola":0.0,
        "nomb_estacion":"ARAGÜÉS DEL PUERTO",
        "provincia":"HUESCA",
        "lat":"424231N",
        "long":"004022W"
    },
    {
        "id_estacion":"9208E",
        "fecha":"2023-05-01",
        "precipitacion_maxima":"33.2(31)",
        "temperatura_media_minima_mensual":7.2,
        "temperatura_media_maxima_mensual":19.1,
        "temperatura_max_absoluta_mes":"26.8(03)",
        "temperatura_min_absoluta_mes":"1.7(12)",
        "temperatura_minima_mas_baja":12.1,
        "tempetatura_mas_baja_mes":12.0,
        "dias_con_precipitacion_mayor_01":12.0,
        "dias_con_precipitacion_mayor_0100":8.0,
        "dias_con_precipitacion_mayor_10":3.0,
        "dias_con_precipitacion_mayor_30":1.0,
        "tension_vapor_media":82.0,
        "precipitacion_total_mes":94.0,
        "dias_temperatura_menor_0":0.0,
        "temperatura_media_mes":13.2,
        "indice_evaporacion":0.1884203078,
        "mes":5,
        "year":2023,
        "indice_solar":0.7,
        "sequia_meteorologica":0.0,
        "sequia_agricola":0.0,
        "nomb_estacion":"ARAGÜÉS DEL PUERTO",
        "provincia":"HUESCA",
        "lat":"424231N",
        "long":"004022W"
    },
    {
        "id_estacion":"9208E",
        "fecha":"2023-06-01",
        "precipitacion_maxima":"43.2(21)",
        "temperatura_media_minima_mensual":12.4,
        "temperatura_media_maxima_mensual":24.0,
        "temperatura_max_absoluta_mes":"31.7(25)",
        "temperatura_min_absoluta_mes":"9.3(04)",
        "temperatura_minima_mas_baja":16.2,
        "tempetatura_mas_baja_mes":16.8,
        "dias_con_precipitacion_mayor_01":19.0,
        "dias_con_precipitacion_mayor_0100":18.0,
        "dias_con_precipitacion_mayor_10":9.0,
        "dias_con_precipitacion_mayor_30":3.0,
        "tension_vapor_media":136.0,
        "precipitacion_total_mes":276.6,
        "dias_temperatura_menor_0":0.0,
        "temperatura_media_mes":18.2,
        "indice_evaporacion":0.0799406862,
        "mes":6,
        "year":2023,
        "indice_solar":0.9,
        "sequia_meteorologica":1.0,
        "sequia_agricola":1.0,
        "nomb_estacion":"ARAGÜÉS DEL PUERTO",
        "provincia":"HUESCA",
        "lat":"424231N",
        "long":"004022W"
    },
    {
        "id_estacion":"9208E",
        "fecha":"2023-07-01",
        "precipitacion_maxima":"43.0(07)",
        "temperatura_media_minima_mensual":14.2,
        "temperatura_media_maxima_mensual":28.5,
        "temperatura_max_absoluta_mes":"34.7(18)",
        "temperatura_min_absoluta_mes":"8.5(26)",
        "temperatura_minima_mas_baja":20.7,
        "tempetatura_mas_baja_mes":19.3,
        "dias_con_precipitacion_mayor_01":7.0,
        "dias_con_precipitacion_mayor_0100":4.0,
        "dias_con_precipitacion_mayor_10":2.0,
        "dias_con_precipitacion_mayor_30":1.0,
        "tension_vapor_media":132.0,
        "precipitacion_total_mes":74.8,
        "dias_temperatura_menor_0":0.0,
        "temperatura_media_mes":21.4,
        "indice_evaporacion":0.3639008455,
        "mes":7,
        "year":2023,
        "indice_solar":1.0,
        "sequia_meteorologica":0.0,
        "sequia_agricola":0.0,
        "nomb_estacion":"ARAGÜÉS DEL PUERTO",
        "provincia":"HUESCA",
        "lat":"424231N",
        "long":"004022W"
    },
    {
        "id_estacion":"9208E",
        "fecha":"2023-08-01",
        "precipitacion_maxima":"6.6(26)",
        "temperatura_media_minima_mensual":15.6,
        "temperatura_media_maxima_mensual":29.6,
        "temperatura_max_absoluta_mes":"37.0(23)",
        "temperatura_min_absoluta_mes":"6.8(31)",
        "temperatura_minima_mas_baja":23.5,
        "tempetatura_mas_baja_mes":17.4,
        "dias_con_precipitacion_mayor_01":6.0,
        "dias_con_precipitacion_mayor_0100":4.0,
        "dias_con_precipitacion_mayor_10":0.0,
        "dias_con_precipitacion_mayor_30":0.0,
        "tension_vapor_media":108.0,
        "precipitacion_total_mes":16.2,
        "dias_temperatura_menor_0":0.0,
        "temperatura_media_mes":22.6,
        "indice_evaporacion":1.0,
        "mes":8,
        "year":2023,
        "indice_solar":0.9,
        "sequia_meteorologica":0.0,
        "sequia_agricola":0.0,
        "nomb_estacion":"ARAGÜÉS DEL PUERTO",
        "provincia":"HUESCA",
        "lat":"424231N",
        "long":"004022W"
    },
    {
        "id_estacion":"9208E",
        "fecha":"2023-09-01",
        "precipitacion_maxima":"39.2(01)",
        "temperatura_media_minima_mensual":13.4,
        "temperatura_media_maxima_mensual":24.9,
        "temperatura_max_absoluta_mes":"30.1(09)",
        "temperatura_min_absoluta_mes":"6.7(23)",
        "temperatura_minima_mas_baja":22.7,
        "tempetatura_mas_baja_mes":14.7,
        "dias_con_precipitacion_mayor_01":13.0,
        "dias_con_precipitacion_mayor_0100":9.0,
        "dias_con_precipitacion_mayor_10":4.0,
        "dias_con_precipitacion_mayor_30":1.0,
        "tension_vapor_media":120.0,
        "precipitacion_total_mes":110.6,
        "dias_temperatura_menor_0":0.0,
        "temperatura_media_mes":19.2,
        "indice_evaporacion":0.2322123971,
        "mes":9,
        "year":2023,
        "indice_solar":0.7,
        "sequia_meteorologica":0.0,
        "sequia_agricola":0.0,
        "nomb_estacion":"ARAGÜÉS DEL PUERTO",
        "provincia":"HUESCA",
        "lat":"424231N",
        "long":"004022W"
    },
    {
        "id_estacion":"9208E",
        "fecha":"2023-10-01",
        "precipitacion_maxima":"48.6(19)",
        "temperatura_media_minima_mensual":10.8,
        "temperatura_media_maxima_mensual":20.1,
        "temperatura_max_absoluta_mes":"29.8(02)",
        "temperatura_min_absoluta_mes":"3.7(21)",
        "temperatura_minima_mas_baja":17.0,
        "tempetatura_mas_baja_mes":10.4,
        "dias_con_precipitacion_mayor_01":15.0,
        "dias_con_precipitacion_mayor_0100":14.0,
        "dias_con_precipitacion_mayor_10":7.0,
        "dias_con_precipitacion_mayor_30":3.0,
        "tension_vapor_media":103.0,
        "precipitacion_total_mes":225.0,
        "dias_temperatura_menor_0":0.0,
        "temperatura_media_mes":15.4,
        "indice_evaporacion":0.0840452824,
        "mes":10,
        "year":2023,
        "indice_solar":0.5,
        "sequia_meteorologica":1.0,
        "sequia_agricola":1.0,
        "nomb_estacion":"ARAGÜÉS DEL PUERTO",
        "provincia":"HUESCA",
        "lat":"424231N",
        "long":"004022W"
    },
    {
        "id_estacion":"9208E",
        "fecha":"2023-11-01",
        "precipitacion_maxima":"40.0(04)",
        "temperatura_media_minima_mensual":4.9,
        "temperatura_media_maxima_mensual":13.3,
        "temperatura_max_absoluta_mes":"21.1(19)",
        "temperatura_min_absoluta_mes":"0.6(03)",
        "temperatura_minima_mas_baja":9.4,
        "tempetatura_mas_baja_mes":5.4,
        "dias_con_precipitacion_mayor_01":17.0,
        "dias_con_precipitacion_mayor_0100":15.0,
        "dias_con_precipitacion_mayor_10":6.0,
        "dias_con_precipitacion_mayor_30":2.0,
        "tension_vapor_media":79.0,
        "precipitacion_total_mes":197.4,
        "dias_temperatura_menor_0":0.0,
        "temperatura_media_mes":9.1,
        "indice_evaporacion":0.0487224424,
        "mes":11,
        "year":2023,
        "indice_solar":0.3,
        "sequia_meteorologica":0.8073333333,
        "sequia_agricola":0.8041461089,
        "nomb_estacion":"ARAGÜÉS DEL PUERTO",
        "provincia":"HUESCA",
        "lat":"424231N",
        "long":"004022W"
    },
    {
        "id_estacion":"9208E",
        "fecha":"2023-12-01",
        "precipitacion_maxima":"28.8(13)",
        "temperatura_media_minima_mensual":2.3,
        "temperatura_media_maxima_mensual":11.5,
        "temperatura_max_absoluta_mes":"16.8(27)",
        "temperatura_min_absoluta_mes":"-3.2(03)",
        "temperatura_minima_mas_baja":8.5,
        "tempetatura_mas_baja_mes":4.3,
        "dias_con_precipitacion_mayor_01":9.0,
        "dias_con_precipitacion_mayor_0100":8.0,
        "dias_con_precipitacion_mayor_10":3.0,
        "dias_con_precipitacion_mayor_30":0.0,
        "tension_vapor_media":61.0,
        "precipitacion_total_mes":75.0,
        "dias_temperatura_menor_0":5.0,
        "temperatura_media_mes":6.9,
        "indice_evaporacion":0.1197163195,
        "mes":12,
        "year":2023,
        "indice_solar":0.2,
        "sequia_meteorologica":0.0,
        "sequia_agricola":0.0,
        "nomb_estacion":"ARAGÜÉS DEL PUERTO",
        "provincia":"HUESCA",
        "lat":"424231N",
        "long":"004022W"
    },
    {
        "id_estacion":"9208E",
        "fecha":"2024-01-01",
        "precipitacion_maxima":"12.4(17)",
        "temperatura_media_minima_mensual":2.0,
        "temperatura_media_maxima_mensual":11.1,
        "temperatura_max_absoluta_mes":"21.8(25)",
        "temperatura_min_absoluta_mes":"-4.9(08)",
        "temperatura_minima_mas_baja":9.4,
        "tempetatura_mas_baja_mes":2.6,
        "dias_con_precipitacion_mayor_01":11.0,
        "dias_con_precipitacion_mayor_0100":9.0,
        "dias_con_precipitacion_mayor_10":1.0,
        "dias_con_precipitacion_mayor_30":0.0,
        "tension_vapor_media":63.0,
        "precipitacion_total_mes":51.2,
        "dias_temperatura_menor_0":11.0,
        "temperatura_media_mes":6.6,
        "indice_evaporacion":0.2404745459,
        "mes":1,
        "year":2024,
        "indice_solar":0.3,
        "sequia_meteorologica":0.0,
        "sequia_agricola":0.0,
        "nomb_estacion":"ARAGÜÉS DEL PUERTO",
        "provincia":"HUESCA",
        "lat":"424231N",
        "long":"004022W"
    },
    {
        "id_estacion":"9208E",
        "fecha":"2024-02-01",
        "precipitacion_maxima":"48.4(25)",
        "temperatura_media_minima_mensual":3.0,
        "temperatura_media_maxima_mensual":12.6,
        "temperatura_max_absoluta_mes":"19.9(04)",
        "temperatura_min_absoluta_mes":"-0.1(24)",
        "temperatura_minima_mas_baja":9.5,
        "tempetatura_mas_baja_mes":4.3,
        "dias_con_precipitacion_mayor_01":15.0,
        "dias_con_precipitacion_mayor_0100":12.0,
        "dias_con_precipitacion_mayor_10":7.0,
        "dias_con_precipitacion_mayor_30":1.0,
        "tension_vapor_media":63.0,
        "precipitacion_total_mes":182.0,
        "dias_temperatura_menor_0":1.0,
        "temperatura_media_mes":7.8,
        "indice_evaporacion":0.0173901057,
        "mes":2,
        "year":2024,
        "indice_solar":0.4,
        "sequia_meteorologica":0.6638333333,
        "sequia_agricola":0.6599594323,
        "nomb_estacion":"ARAGÜÉS DEL PUERTO",
        "provincia":"HUESCA",
        "lat":"424231N",
        "long":"004022W"
    },
    {
        "id_estacion":"9208E",
        "fecha":"2024-03-01",
        "precipitacion_maxima":"38.0(02)",
        "temperatura_media_minima_mensual":3.0,
        "temperatura_media_maxima_mensual":12.9,
        "temperatura_max_absoluta_mes":"24.7(22)",
        "temperatura_min_absoluta_mes":"-3.1(04)",
        "temperatura_minima_mas_baja":10.1,
        "tempetatura_mas_baja_mes":3.7,
        "dias_con_precipitacion_mayor_01":19.0,
        "dias_con_precipitacion_mayor_0100":18.0,
        "dias_con_precipitacion_mayor_10":8.0,
        "dias_con_precipitacion_mayor_30":2.0,
        "tension_vapor_media":69.0,
        "precipitacion_total_mes":218.0,
        "dias_temperatura_menor_0":7.0,
        "temperatura_media_mes":8.0,
        "indice_evaporacion":0.0,
        "mes":3,
        "year":2024,
        "indice_solar":0.5,
        "sequia_meteorologica":1.0,
        "sequia_agricola":1.0,
        "nomb_estacion":"ARAGÜÉS DEL PUERTO",
        "provincia":"HUESCA",
        "lat":"424231N",
        "long":"004022W"
    },
    {
        "id_estacion":"9208E",
        "fecha":"2024-04-01",
        "precipitacion_maxima":"6.2(02)",
        "temperatura_media_minima_mensual":5.3,
        "temperatura_media_maxima_mensual":16.4,
        "temperatura_max_absoluta_mes":"26.8(13)",
        "temperatura_min_absoluta_mes":"0.3(25)",
        "temperatura_minima_mas_baja":14.3,
        "tempetatura_mas_baja_mes":8.1,
        "dias_con_precipitacion_mayor_01":10.0,
        "dias_con_precipitacion_mayor_0100":9.0,
        "dias_con_precipitacion_mayor_10":0.0,
        "dias_con_precipitacion_mayor_30":0.0,
        "tension_vapor_media":64.0,
        "precipitacion_total_mes":32.2,
        "dias_temperatura_menor_0":0.0,
        "temperatura_media_mes":10.8,
        "indice_evaporacion":0.6585453878,
        "mes":4,
        "year":2024,
        "indice_solar":0.6,
        "sequia_meteorologica":0.0,
        "sequia_agricola":0.0,
        "nomb_estacion":"ARAGÜÉS DEL PUERTO",
        "provincia":"HUESCA",
        "lat":"424231N",
        "long":"004022W"
    },
    {
        "id_estacion":"9208E",
        "fecha":"2024-05-01",
        "precipitacion_maxima":"27.0(18)",
        "temperatura_media_minima_mensual":6.8,
        "temperatura_media_maxima_mensual":18.6,
        "temperatura_max_absoluta_mes":"26.0(11)",
        "temperatura_min_absoluta_mes":"1.5(02)",
        "temperatura_minima_mas_baja":13.3,
        "tempetatura_mas_baja_mes":10.2,
        "dias_con_precipitacion_mayor_01":15.0,
        "dias_con_precipitacion_mayor_0100":11.0,
        "dias_con_precipitacion_mayor_10":5.0,
        "dias_con_precipitacion_mayor_30":0.0,
        "tension_vapor_media":86.0,
        "precipitacion_total_mes":123.8,
        "dias_temperatura_menor_0":0.0,
        "temperatura_media_mes":12.7,
        "indice_evaporacion":0.1759321417,
        "mes":5,
        "year":2024,
        "indice_solar":0.7,
        "sequia_meteorologica":0.0818333333,
        "sequia_agricola":0.0733740119,
        "nomb_estacion":"ARAGÜÉS DEL PUERTO",
        "provincia":"HUESCA",
        "lat":"424231N",
        "long":"004022W"
    },
    {
        "id_estacion":"9208E",
        "fecha":"2024-06-01",
        "precipitacion_maxima":"24.8(19)",
        "temperatura_media_minima_mensual":11.6,
        "temperatura_media_maxima_mensual":23.9,
        "temperatura_max_absoluta_mes":"30.3(27)",
        "temperatura_min_absoluta_mes":"5.6(13)",
        "temperatura_minima_mas_baja":18.2,
        "tempetatura_mas_baja_mes":15.6,
        "dias_con_precipitacion_mayor_01":7.0,
        "dias_con_precipitacion_mayor_0100":7.0,
        "dias_con_precipitacion_mayor_10":2.0,
        "dias_con_precipitacion_mayor_30":0.0,
        "tension_vapor_media":111.0,
        "precipitacion_total_mes":62.6,
        "dias_temperatura_menor_0":0.0,
        "temperatura_media_mes":17.8,
        "indice_evaporacion":0.5676837551,
        "mes":6,
        "year":2024,
        "indice_solar":0.9,
        "sequia_meteorologica":0.0,
        "sequia_agricola":0.0,
        "nomb_estacion":"ARAGÜÉS DEL PUERTO",
        "provincia":"HUESCA",
        "lat":"424231N",
        "long":"004022W"
    },
    {
        "id_estacion":"9208E",
        "fecha":"2024-07-01",
        "precipitacion_maxima":"24.2(05)",
        "temperatura_media_minima_mensual":14.9,
        "temperatura_media_maxima_mensual":29.1,
        "temperatura_max_absoluta_mes":"35.4(29)",
        "temperatura_min_absoluta_mes":"7.2(22)",
        "temperatura_minima_mas_baja":21.6,
        "tempetatura_mas_baja_mes":20.8,
        "dias_con_precipitacion_mayor_01":5.0,
        "dias_con_precipitacion_mayor_0100":5.0,
        "dias_con_precipitacion_mayor_10":1.0,
        "dias_con_precipitacion_mayor_30":0.0,
        "tension_vapor_media":124.0,
        "precipitacion_total_mes":38.6,
        "dias_temperatura_menor_0":0.0,
        "temperatura_media_mes":22.0,
        "indice_evaporacion":1.0,
        "mes":7,
        "year":2024,
        "indice_solar":1.0,
        "sequia_meteorologica":0.0,
        "sequia_agricola":0.0,
        "nomb_estacion":"ARAGÜÉS DEL PUERTO",
        "provincia":"HUESCA",
        "lat":"424231N",
        "long":"004022W"
    },
    {
        "id_estacion":"9208E",
        "fecha":"2024-08-01",
        "precipitacion_maxima":"97.6(31)",
        "temperatura_media_minima_mensual":null,
        "temperatura_media_maxima_mensual":null,
        "temperatura_max_absoluta_mes":null,
        "temperatura_min_absoluta_mes":null,
        "temperatura_minima_mas_baja":null,
        "tempetatura_mas_baja_mes":null,
        "dias_con_precipitacion_mayor_01":7.0,
        "dias_con_precipitacion_mayor_0100":6.0,
        "dias_con_precipitacion_mayor_10":4.0,
        "dias_con_precipitacion_mayor_30":1.0,
        "tension_vapor_media":null,
        "precipitacion_total_mes":148.6,
        "dias_temperatura_menor_0":null,
        "temperatura_media_mes":null,
        "indice_evaporacion":null,
        "mes":8,
        "year":2024,
        "indice_solar":0.9,
        "sequia_meteorologica":0.3298333333,
        "sequia_agricola":0.5,
        "nomb_estacion":"ARAGÜÉS DEL PUERTO",
        "provincia":"HUESCA",
        "lat":"424231N",
        "long":"004022W"
    },
    {
        "id_estacion":"9208E",
        "fecha":"2024-09-01",
        "precipitacion_maxima":"97.2(06)",
        "temperatura_media_minima_mensual":9.5,
        "temperatura_media_maxima_mensual":19.8,
        "temperatura_max_absoluta_mes":"27.0(02)",
        "temperatura_min_absoluta_mes":"3.8(28)",
        "temperatura_minima_mas_baja":14.5,
        "tempetatura_mas_baja_mes":13.7,
        "dias_con_precipitacion_mayor_01":14.0,
        "dias_con_precipitacion_mayor_0100":11.0,
        "dias_con_precipitacion_mayor_10":5.0,
        "dias_con_precipitacion_mayor_30":1.0,
        "tension_vapor_media":112.0,
        "precipitacion_total_mes":193.4,
        "dias_temperatura_menor_0":0.0,
        "temperatura_media_mes":14.7,
        "indice_evaporacion":0.1075604242,
        "mes":9,
        "year":2024,
        "indice_solar":0.7,
        "sequia_meteorologica":0.7778333333,
        "sequia_agricola":0.7700577291,
        "nomb_estacion":"ARAGÜÉS DEL PUERTO",
        "provincia":"HUESCA",
        "lat":"424231N",
        "long":"004022W"
    },
    {
        "id_estacion":"9208E",
        "fecha":"2024-10-01",
        "precipitacion_maxima":"45.4(25)",
        "temperatura_media_minima_mensual":8.7,
        "temperatura_media_maxima_mensual":17.1,
        "temperatura_max_absoluta_mes":"23.0(01)",
        "temperatura_min_absoluta_mes":"3.1(04)",
        "temperatura_minima_mas_baja":15.6,
        "tempetatura_mas_baja_mes":9.9,
        "dias_con_precipitacion_mayor_01":20.0,
        "dias_con_precipitacion_mayor_0100":16.0,
        "dias_con_precipitacion_mayor_10":9.0,
        "dias_con_precipitacion_mayor_30":1.0,
        "tension_vapor_media":118.0,
        "precipitacion_total_mes":210.2,
        "dias_temperatura_menor_0":0.0,
        "temperatura_media_mes":13.0,
        "indice_evaporacion":0.0697278564,
        "mes":10,
        "year":2024,
        "indice_solar":0.5,
        "sequia_meteorologica":0.9458333333,
        "sequia_agricola":0.9404360548,
        "nomb_estacion":"ARAGÜÉS DEL PUERTO",
        "provincia":"HUESCA",
        "lat":"424231N",
        "long":"004022W"
    },
    {
        "id_estacion":"9208E",
        "fecha":"2024-11-01",
        "precipitacion_maxima":"21.2(04)",
        "temperatura_media_minima_mensual":5.0,
        "temperatura_media_maxima_mensual":14.5,
        "temperatura_max_absoluta_mes":"19.3(01)",
        "temperatura_min_absoluta_mes":"-0.8(13)",
        "temperatura_minima_mas_baja":10.3,
        "tempetatura_mas_baja_mes":8.7,
        "dias_con_precipitacion_mayor_01":8.0,
        "dias_con_precipitacion_mayor_0100":7.0,
        "dias_con_precipitacion_mayor_10":3.0,
        "dias_con_precipitacion_mayor_30":0.0,
        "tension_vapor_media":91.0,
        "precipitacion_total_mes":54.8,
        "dias_temperatura_menor_0":3.0,
        "temperatura_media_mes":9.8,
        "indice_evaporacion":0.3549787539,
        "mes":11,
        "year":2024,
        "indice_solar":0.3,
        "sequia_meteorologica":0.0,
        "sequia_agricola":0.0,
        "nomb_estacion":"ARAGÜÉS DEL PUERTO",
        "provincia":"HUESCA",
        "lat":"424231N",
        "long":"004022W"
    },
    {
        "id_estacion":"9208E",
        "fecha":"2024-12-01",
        "precipitacion_maxima":"26.2(07)",
        "temperatura_media_minima_mensual":1.4,
        "temperatura_media_maxima_mensual":10.4,
        "temperatura_max_absoluta_mes":"17.1(01)",
        "temperatura_min_absoluta_mes":"-2.2(10)",
        "temperatura_minima_mas_baja":8.0,
        "tempetatura_mas_baja_mes":1.7,
        "dias_con_precipitacion_mayor_01":10.0,
        "dias_con_precipitacion_mayor_0100":8.0,
        "dias_con_precipitacion_mayor_10":2.0,
        "dias_con_precipitacion_mayor_30":0.0,
        "tension_vapor_media":64.0,
        "precipitacion_total_mes":72.0,
        "dias_temperatura_menor_0":12.0,
        "temperatura_media_mes":5.9,
        "indice_evaporacion":0.1231233425,
        "mes":12,
        "year":2024,
        "indice_solar":0.2,
        "sequia_meteorologica":0.0,
        "sequia_agricola":0.0,
        "nomb_estacion":"ARAGÜÉS DEL PUERTO",
        "provincia":"HUESCA",
        "lat":"424231N",
        "long":"004022W"
    }
]