{"id_estacion":"5406X","fecha":"2024-10-01","precipitación_máxima":"11.6(29)","temperatura_media_minima_mensual":11.0,"temperatura_media_maxima_mensual":21.0,"temperatura_max_absoluta_mes":"28.4(06)","temperatura_min_absoluta_mes":"3.1(28)","temperatura_minima_mas_baja":16.1,"tempetatura_mas_baja_mes":11.4,"dias_con_precipitacion_mayor_01":14,"dias_con_precipitacion_mayor_0100":12,"dias_con_precipitacion_mayor_10":1,"dias_con_precipitacion_mayor_30":0,"tension_vapor_media":128,"precipitacion_total_mes":61.6,"dias_temperatura_menor_0":0,"temperatura_media_mes":16.0,"indice_evaporacion":0.1639857008,"mes":10,"indice_solar":0.5,"sequia_meteorologica":0.0901666667,"sequia_agrícola":0.0838268097}
{"id_estacion":"5406X","fecha":"2024-11-01","precipitación_máxima":"57.4(13)","temperatura_media_minima_mensual":9.0,"temperatura_media_maxima_mensual":18.7,"temperatura_max_absoluta_mes":"23.5(06)","temperatura_min_absoluta_mes":"6.7(12)","temperatura_minima_mas_baja":11.5,"tempetatura_mas_baja_mes":9.3,"dias_con_precipitacion_mayor_01":11,"dias_con_precipitacion_mayor_0100":2,"dias_con_precipitacion_mayor_10":1,"dias_con_precipitacion_mayor_30":1,"tension_vapor_media":108,"precipitacion_total_mes":63.4,"dias_temperatura_menor_0":0,"temperatura_media_mes":13.9,"indice_evaporacion":0.1362173368,"mes":11,"indice_solar":0.3,"sequia_meteorologica":0.1081666667,"sequia_agrícola":0.1041044933}
{"id_estacion":"5406X","fecha":"2024-01-01","precipitación_máxima":"11.0(04)","temperatura_media_minima_mensual":5.3,"temperatura_media_maxima_mensual":15.4,"temperatura_max_absoluta_mes":"25.7(25)","temperatura_min_absoluta_mes":"-1.7(08)","temperatura_minima_mas_baja":10.1,"tempetatura_mas_baja_mes":8.1,"dias_con_precipitacion_mayor_01":11,"dias_con_precipitacion_mayor_0100":6,"dias_con_precipitacion_mayor_10":1,"dias_con_precipitacion_mayor_30":0,"tension_vapor_media":83,"precipitacion_total_mes":32.2,"dias_temperatura_menor_0":2,"temperatura_media_mes":10.4,"indice_evaporacion":0.2039488108,"mes":1,"indice_solar":0.3,"sequia_meteorologica":0.0,"sequia_agrícola":0.0}
{"id_estacion":"5406X","fecha":"2024-02-01","precipitación_máxima":"34.8(09)","temperatura_media_minima_mensual":5.2,"temperatura_media_maxima_mensual":14.9,"temperatura_max_absoluta_mes":"21.1(14)","temperatura_min_absoluta_mes":"-0.7(28)","temperatura_minima_mas_baja":11.4,"tempetatura_mas_baja_mes":8.6,"dias_con_precipitacion_mayor_01":15,"dias_con_precipitacion_mayor_0100":10,"dias_con_precipitacion_mayor_10":5,"dias_con_precipitacion_mayor_30":1,"tension_vapor_media":82,"precipitacion_total_mes":110.8,"dias_temperatura_menor_0":1,"temperatura_media_mes":10.1,"indice_evaporacion":0.0348202745,"mes":2,"indice_solar":0.4,"sequia_meteorologica":0.5821666667,"sequia_agrícola":0.5781184639}
{"id_estacion":"5406X","fecha":"2024-03-01","precipitación_máxima":"29.6(30)","temperatura_media_minima_mensual":6.5,"temperatura_media_maxima_mensual":15.8,"temperatura_max_absoluta_mes":"26.6(17)","temperatura_min_absoluta_mes":"0.0(01)","temperatura_minima_mas_baja":18.2,"tempetatura_mas_baja_mes":7.7,"dias_con_precipitacion_mayor_01":18,"dias_con_precipitacion_mayor_0100":14,"dias_con_precipitacion_mayor_10":9,"dias_con_precipitacion_mayor_30":0,"tension_vapor_media":88,"precipitacion_total_mes":208.8,"dias_temperatura_menor_0":1,"temperatura_media_mes":11.1,"indice_evaporacion":0.0,"mes":3,"indice_solar":0.5,"sequia_meteorologica":1.5621666667,"sequia_agrícola":1.5574666667}
{"id_estacion":"5406X","fecha":"2024-04-01","precipitación_máxima":"102.8(20)","temperatura_media_minima_mensual":8.4,"temperatura_media_maxima_mensual":20.9,"temperatura_max_absoluta_mes":"28.2(05)","temperatura_min_absoluta_mes":"3.8(09)","temperatura_minima_mas_baja":14.6,"tempetatura_mas_baja_mes":13.5,"dias_con_precipitacion_mayor_01":6,"dias_con_precipitacion_mayor_0100":4,"dias_con_precipitacion_mayor_10":2,"dias_con_precipitacion_mayor_30":1,"tension_vapor_media":93,"precipitacion_total_mes":123.6,"dias_temperatura_menor_0":0,"temperatura_media_mes":14.7,"indice_evaporacion":0.0587802803,"mes":4,"indice_solar":0.6,"sequia_meteorologica":0.7101666667,"sequia_agrícola":0.7038788639}
{"id_estacion":"5406X","fecha":"2024-05-01","precipitación_máxima":"7.2(01)","temperatura_media_minima_mensual":10.3,"temperatura_media_maxima_mensual":24.4,"temperatura_max_absoluta_mes":"33.6(30)","temperatura_min_absoluta_mes":"2.6(02)","temperatura_minima_mas_baja":18.4,"tempetatura_mas_baja_mes":12.5,"dias_con_precipitacion_mayor_01":3,"dias_con_precipitacion_mayor_0100":1,"dias_con_precipitacion_mayor_10":0,"dias_con_precipitacion_mayor_30":0,"tension_vapor_media":100,"precipitacion_total_mes":7.8,"dias_temperatura_menor_0":0,"temperatura_media_mes":17.4,"indice_evaporacion":0.6740215992,"mes":5,"indice_solar":0.7,"sequia_meteorologica":0.0,"sequia_agrícola":0.0}
{"id_estacion":"5406X","fecha":"2024-06-01","precipitación_máxima":"6.0(07)","temperatura_media_minima_mensual":14.1,"temperatura_media_maxima_mensual":27.6,"temperatura_max_absoluta_mes":"34.8(06)","temperatura_min_absoluta_mes":"9.2(20)","temperatura_minima_mas_baja":18.3,"tempetatura_mas_baja_mes":21.0,"dias_con_precipitacion_mayor_01":2,"dias_con_precipitacion_mayor_0100":1,"dias_con_precipitacion_mayor_10":0,"dias_con_precipitacion_mayor_30":0,"tension_vapor_media":129,"precipitacion_total_mes":6.8,"dias_temperatura_menor_0":0,"temperatura_media_mes":20.9,"indice_evaporacion":0.7414623087,"mes":6,"indice_solar":0.9,"sequia_meteorologica":0.0,"sequia_agrícola":0.0}
{"id_estacion":"5406X","fecha":"2024-07-01","precipitación_máxima":"0.0(--)","temperatura_media_minima_mensual":18.7,"temperatura_media_maxima_mensual":34.6,"temperatura_max_absoluta_mes":"38.7(24)","temperatura_min_absoluta_mes":"13.8(01)","temperatura_minima_mas_baja":24.5,"tempetatura_mas_baja_mes":25.2,"dias_con_precipitacion_mayor_01":0,"dias_con_precipitacion_mayor_0100":0,"dias_con_precipitacion_mayor_10":0,"dias_con_precipitacion_mayor_30":0,"tension_vapor_media":136,"precipitacion_total_mes":0.0,"dias_temperatura_menor_0":0,"temperatura_media_mes":26.6,"indice_evaporacion":1.0,"mes":7,"indice_solar":1.0,"sequia_meteorologica":0.0,"sequia_agrícola":0.0}
{"id_estacion":"5406X","fecha":"2024-08-01","precipitación_máxima":"1.2(28)","temperatura_media_minima_mensual":19.4,"temperatura_media_maxima_mensual":34.8,"temperatura_max_absoluta_mes":"38.3(10)","temperatura_min_absoluta_mes":"15.9(14)","temperatura_minima_mas_baja":22.5,"tempetatura_mas_baja_mes":30.2,"dias_con_precipitacion_mayor_01":2,"dias_con_precipitacion_mayor_0100":1,"dias_con_precipitacion_mayor_10":0,"dias_con_precipitacion_mayor_30":0,"tension_vapor_media":146,"precipitacion_total_mes":1.4,"dias_temperatura_menor_0":0,"temperatura_media_mes":27.1,"indice_evaporacion":0.9482658036,"mes":8,"indice_solar":0.9,"sequia_meteorologica":0.0,"sequia_agrícola":0.0}
{"id_estacion":"5406X","fecha":"2024-09-01","precipitación_máxima":"7.2(07)","temperatura_media_minima_mensual":13.9,"temperatura_media_maxima_mensual":27.1,"temperatura_max_absoluta_mes":"31.5(03)","temperatura_min_absoluta_mes":"7.9(28)","temperatura_minima_mas_baja":20.5,"tempetatura_mas_baja_mes":20.6,"dias_con_precipitacion_mayor_01":6,"dias_con_precipitacion_mayor_0100":3,"dias_con_precipitacion_mayor_10":0,"dias_con_precipitacion_mayor_30":0,"tension_vapor_media":130,"precipitacion_total_mes":11.6,"dias_temperatura_menor_0":0,"temperatura_media_mes":20.5,"indice_evaporacion":0.6194185205,"mes":9,"indice_solar":0.7,"sequia_meteorologica":0.0,"sequia_agrícola":0.0}
{"id_estacion":"5406X","fecha":"2024-12-01","precipitación_máxima":"1.8(12)","temperatura_media_minima_mensual":3.4,"temperatura_media_maxima_mensual":14.8,"temperatura_max_absoluta_mes":"21.8(18)","temperatura_min_absoluta_mes":"-1.4(10)","temperatura_minima_mas_baja":10.0,"tempetatura_mas_baja_mes":8.6,"dias_con_precipitacion_mayor_01":4,"dias_con_precipitacion_mayor_0100":1,"dias_con_precipitacion_mayor_10":0,"dias_con_precipitacion_mayor_30":0,"tension_vapor_media":69,"precipitacion_total_mes":3.0,"dias_temperatura_menor_0":3,"temperatura_media_mes":9.1,"indice_evaporacion":0.738885361,"mes":12,"indice_solar":0.2,"sequia_meteorologica":0.0,"sequia_agrícola":0.0}
