{"id_estacion":"3229Y","fecha":"2024-10-01","precipitación_máxima":"27.0(16)","temperatura_media_minima_mensual":10.6,"temperatura_media_maxima_mensual":21.1,"temperatura_max_absoluta_mes":"27.9(01)","temperatura_min_absoluta_mes":"4.6(26)","temperatura_minima_mas_baja":16.2,"tempetatura_mas_baja_mes":14.2,"dias_con_precipitacion_mayor_01":13,"dias_con_precipitacion_mayor_0100":11,"dias_con_precipitacion_mayor_10":6,"dias_con_precipitacion_mayor_30":0,"tension_vapor_media":130,"precipitacion_total_mes":132.8,"dias_temperatura_menor_0":0,"temperatura_media_mes":15.8,"indice_evaporacion":0.0349734589,"mes":10,"indice_solar":0.5,"sequia_meteorologica":0.968,"sequia_agrícola":0.9629502654}
{"id_estacion":"3229Y","fecha":"2024-11-01","precipitación_máxima":"2.8(25)","temperatura_media_minima_mensual":6.7,"temperatura_media_maxima_mensual":17.2,"temperatura_max_absoluta_mes":"20.7(06)","temperatura_min_absoluta_mes":"-0.1(28)","temperatura_minima_mas_baja":12.7,"tempetatura_mas_baja_mes":11.3,"dias_con_precipitacion_mayor_01":4,"dias_con_precipitacion_mayor_0100":2,"dias_con_precipitacion_mayor_10":0,"dias_con_precipitacion_mayor_30":0,"tension_vapor_media":108,"precipitacion_total_mes":5.0,"dias_temperatura_menor_0":1,"temperatura_media_mes":11.9,"indice_evaporacion":0.7627828222,"mes":11,"indice_solar":0.3,"sequia_meteorologica":0.0,"sequia_agrícola":0.0}
{"id_estacion":"3229Y","fecha":"2024-01-01","precipitación_máxima":"18.4(19)","temperatura_media_minima_mensual":2.9,"temperatura_media_maxima_mensual":12.5,"temperatura_max_absoluta_mes":"20.1(26)","temperatura_min_absoluta_mes":"-4.8(08)","temperatura_minima_mas_baja":11.5,"tempetatura_mas_baja_mes":7.5,"dias_con_precipitacion_mayor_01":12,"dias_con_precipitacion_mayor_0100":10,"dias_con_precipitacion_mayor_10":2,"dias_con_precipitacion_mayor_30":0,"tension_vapor_media":90,"precipitacion_total_mes":61.8,"dias_temperatura_menor_0":8,"temperatura_media_mes":7.7,"indice_evaporacion":0.0404101544,"mes":1,"indice_solar":0.3,"sequia_meteorologica":0.258,"sequia_agrícola":0.2548958985}
{"id_estacion":"3229Y","fecha":"2024-02-01","precipitación_máxima":"9.2(08)","temperatura_media_minima_mensual":3.1,"temperatura_media_maxima_mensual":15.3,"temperatura_max_absoluta_mes":"20.3(14)","temperatura_min_absoluta_mes":"-1.5(01)","temperatura_minima_mas_baja":8.8,"tempetatura_mas_baja_mes":9.1,"dias_con_precipitacion_mayor_01":7,"dias_con_precipitacion_mayor_0100":5,"dias_con_precipitacion_mayor_10":0,"dias_con_precipitacion_mayor_30":0,"tension_vapor_media":82,"precipitacion_total_mes":21.4,"dias_temperatura_menor_0":5,"temperatura_media_mes":9.2,"indice_evaporacion":0.2715573157,"mes":2,"indice_solar":0.4,"sequia_meteorologica":0.0,"sequia_agrícola":0.0}
{"id_estacion":"3229Y","fecha":"2024-03-01","precipitación_máxima":"20.2(28)","temperatura_media_minima_mensual":4.7,"temperatura_media_maxima_mensual":16.5,"temperatura_max_absoluta_mes":"26.0(22)","temperatura_min_absoluta_mes":"-1.4(01)","temperatura_minima_mas_baja":12.1,"tempetatura_mas_baja_mes":8.9,"dias_con_precipitacion_mayor_01":16,"dias_con_precipitacion_mayor_0100":14,"dias_con_precipitacion_mayor_10":4,"dias_con_precipitacion_mayor_30":0,"tension_vapor_media":91,"precipitacion_total_mes":126.0,"dias_temperatura_menor_0":3,"temperatura_media_mes":10.6,"indice_evaporacion":0.0,"mes":3,"indice_solar":0.5,"sequia_meteorologica":0.9,"sequia_agrícola":0.8953}
{"id_estacion":"3229Y","fecha":"2024-04-01","precipitación_máxima":"3.4(29)","temperatura_media_minima_mensual":6.2,"temperatura_media_maxima_mensual":21.7,"temperatura_max_absoluta_mes":"28.7(15)","temperatura_min_absoluta_mes":"2.1(02)","temperatura_minima_mas_baja":14.5,"tempetatura_mas_baja_mes":13.7,"dias_con_precipitacion_mayor_01":4,"dias_con_precipitacion_mayor_0100":2,"dias_con_precipitacion_mayor_10":0,"dias_con_precipitacion_mayor_30":0,"tension_vapor_media":84,"precipitacion_total_mes":7.0,"dias_temperatura_menor_0":0,"temperatura_media_mes":14.0,"indice_evaporacion":0.7171586842,"mes":4,"indice_solar":0.6,"sequia_meteorologica":0.0,"sequia_agrícola":0.0}
{"id_estacion":"3229Y","fecha":"2024-05-01","precipitación_máxima":"5.2(05)","temperatura_media_minima_mensual":8.7,"temperatura_media_maxima_mensual":25.4,"temperatura_max_absoluta_mes":"34.2(30)","temperatura_min_absoluta_mes":"1.4(02)","temperatura_minima_mas_baja":16.8,"tempetatura_mas_baja_mes":16.7,"dias_con_precipitacion_mayor_01":3,"dias_con_precipitacion_mayor_0100":1,"dias_con_precipitacion_mayor_10":0,"dias_con_precipitacion_mayor_30":0,"tension_vapor_media":93,"precipitacion_total_mes":6.4,"dias_temperatura_menor_0":0,"temperatura_media_mes":17.1,"indice_evaporacion":0.7914143462,"mes":5,"indice_solar":0.7,"sequia_meteorologica":0.0,"sequia_agrícola":0.0}
{"id_estacion":"3229Y","fecha":"2024-06-01","precipitación_máxima":"14.2(09)","temperatura_media_minima_mensual":14.6,"temperatura_media_maxima_mensual":29.3,"temperatura_max_absoluta_mes":"35.9(25)","temperatura_min_absoluta_mes":"10.1(16)","temperatura_minima_mas_baja":21.5,"tempetatura_mas_baja_mes":19.7,"dias_con_precipitacion_mayor_01":9,"dias_con_precipitacion_mayor_0100":5,"dias_con_precipitacion_mayor_10":2,"dias_con_precipitacion_mayor_30":0,"tension_vapor_media":125,"precipitacion_total_mes":36.8,"dias_temperatura_menor_0":0,"temperatura_media_mes":22.0,"indice_evaporacion":0.3610349457,"mes":6,"indice_solar":0.9,"sequia_meteorologica":0.008,"sequia_agrícola":0.0}
{"id_estacion":"3229Y","fecha":"2024-07-01","precipitación_máxima":"3.0(29)","temperatura_media_minima_mensual":17.4,"temperatura_media_maxima_mensual":35.9,"temperatura_max_absoluta_mes":"40.7(24)","temperatura_min_absoluta_mes":"13.4(01)","temperatura_minima_mas_baja":22.7,"tempetatura_mas_baja_mes":30.9,"dias_con_precipitacion_mayor_01":1,"dias_con_precipitacion_mayor_0100":1,"dias_con_precipitacion_mayor_10":0,"dias_con_precipitacion_mayor_30":0,"tension_vapor_media":121,"precipitacion_total_mes":3.0,"dias_temperatura_menor_0":0,"temperatura_media_mes":26.7,"indice_evaporacion":1.0,"mes":7,"indice_solar":1.0,"sequia_meteorologica":0.0,"sequia_agrícola":0.0}
{"id_estacion":"3229Y","fecha":"2024-08-01","precipitación_máxima":"4.2(28)","temperatura_media_minima_mensual":19.3,"temperatura_media_maxima_mensual":35.5,"temperatura_max_absoluta_mes":"39.1(09)","temperatura_min_absoluta_mes":"14.6(16)","temperatura_minima_mas_baja":24.9,"tempetatura_mas_baja_mes":28.7,"dias_con_precipitacion_mayor_01":3,"dias_con_precipitacion_mayor_0100":3,"dias_con_precipitacion_mayor_10":0,"dias_con_precipitacion_mayor_30":0,"tension_vapor_media":136,"precipitacion_total_mes":8.8,"dias_temperatura_menor_0":0,"temperatura_media_mes":27.4,"indice_evaporacion":0.8270205453,"mes":8,"indice_solar":0.9,"sequia_meteorologica":0.0,"sequia_agrícola":0.0}
{"id_estacion":"3229Y","fecha":"2024-09-01","precipitación_máxima":"9.4(04)","temperatura_media_minima_mensual":12.5,"temperatura_media_maxima_mensual":26.9,"temperatura_max_absoluta_mes":"32.4(02)","temperatura_min_absoluta_mes":"6.2(28)","temperatura_minima_mas_baja":19.4,"tempetatura_mas_baja_mes":21.8,"dias_con_precipitacion_mayor_01":5,"dias_con_precipitacion_mayor_0100":5,"dias_con_precipitacion_mayor_10":0,"dias_con_precipitacion_mayor_30":0,"tension_vapor_media":116,"precipitacion_total_mes":21.4,"dias_temperatura_menor_0":0,"temperatura_media_mes":19.8,"indice_evaporacion":0.4906112872,"mes":9,"indice_solar":0.7,"sequia_meteorologica":0.0,"sequia_agrícola":0.0}
{"id_estacion":"3229Y","fecha":"2024-12-01","precipitación_máxima":"1.0(19)","temperatura_media_minima_mensual":0.2,"temperatura_media_maxima_mensual":12.8,"temperatura_max_absoluta_mes":"17.1(07)","temperatura_min_absoluta_mes":"-3.6(21)","temperatura_minima_mas_baja":6.6,"tempetatura_mas_baja_mes":7.0,"dias_con_precipitacion_mayor_01":4,"dias_con_precipitacion_mayor_0100":1,"dias_con_precipitacion_mayor_10":0,"dias_con_precipitacion_mayor_30":0,"tension_vapor_media":72,"precipitacion_total_mes":1.6,"dias_temperatura_menor_0":17,"temperatura_media_mes":6.5,"indice_evaporacion":0.8824902174,"mes":12,"indice_solar":0.2,"sequia_meteorologica":0.0,"sequia_agrícola":0.0}
