{"id_estacion":"1465U","fecha":1601510400000,"precipitación_máxima":"29.8(24)","temperatura_media_minima_mensual":8.9,"temperatura_media_maxima_mensual":16.3,"temperatura_max_absoluta_mes":"21.3(18)","temperatura_min_absoluta_mes":"2.6(16)","temperatura_minima_mas_baja":15.2,"tempetatura_mas_baja_mes":12.1,"dias_con_precipitacion_mayor_01":22.0,"dias_con_precipitacion_mayor_0100":16.0,"dias_con_precipitacion_mayor_10":6.0,"dias_con_precipitacion_mayor_30":0.0,"tension_vapor_media":128,"precipitacion_total_mes":127.2,"dias_temperatura_menor_0":0,"temperatura_media_mes":12.6,"indice_evaporacion":0.0401644905,"mes":10,"indice_solar":0.5,"sequia_meteorologica":0.4662,"sequia_agrícola":0.4610983551}
{"id_estacion":"1465U","fecha":1604188800000,"precipitación_máxima":"18.0(24)","temperatura_media_minima_mensual":7.1,"temperatura_media_maxima_mensual":15.9,"temperatura_max_absoluta_mes":"19.7(21)","temperatura_min_absoluta_mes":"0.2(04)","temperatura_minima_mas_baja":16.1,"tempetatura_mas_baja_mes":10.7,"dias_con_precipitacion_mayor_01":19.0,"dias_con_precipitacion_mayor_0100":11.0,"dias_con_precipitacion_mayor_10":3.0,"dias_con_precipitacion_mayor_30":0.0,"tension_vapor_media":119,"precipitacion_total_mes":86.4,"dias_temperatura_menor_0":0,"temperatura_media_mes":11.6,"indice_evaporacion":0.0705876454,"mes":11,"indice_solar":0.3,"sequia_meteorologica":0.0582,"sequia_agrícola":0.0547941235}
{"id_estacion":"1465U","fecha":1606780800000,"precipitación_máxima":null,"temperatura_media_minima_mensual":4.4,"temperatura_media_maxima_mensual":10.6,"temperatura_max_absoluta_mes":"16.2(01)","temperatura_min_absoluta_mes":"-2.8(26)","temperatura_minima_mas_baja":11.7,"tempetatura_mas_baja_mes":5.5,"dias_con_precipitacion_mayor_01":null,"dias_con_precipitacion_mayor_0100":null,"dias_con_precipitacion_mayor_10":null,"dias_con_precipitacion_mayor_30":null,"tension_vapor_media":98,"precipitacion_total_mes":null,"dias_temperatura_menor_0":5,"temperatura_media_mes":7.5,"indice_evaporacion":null,"mes":12,"indice_solar":0.2,"sequia_meteorologica":null,"sequia_agrícola":null}
{"id_estacion":"1465U","fecha":1577836800000,"precipitación_máxima":"29.2(16)","temperatura_media_minima_mensual":3.5,"temperatura_media_maxima_mensual":11.9,"temperatura_max_absoluta_mes":"16.1(31)","temperatura_min_absoluta_mes":"-3.3(01)","temperatura_minima_mas_baja":12.4,"tempetatura_mas_baja_mes":7.3,"dias_con_precipitacion_mayor_01":25.0,"dias_con_precipitacion_mayor_0100":11.0,"dias_con_precipitacion_mayor_10":7.0,"dias_con_precipitacion_mayor_30":0.0,"tension_vapor_media":94,"precipitacion_total_mes":138.0,"dias_temperatura_menor_0":9,"temperatura_media_mes":7.7,"indice_evaporacion":0.0,"mes":1,"indice_solar":0.3,"sequia_meteorologica":0.5742,"sequia_agrícola":0.5715}
{"id_estacion":"1465U","fecha":1580515200000,"precipitación_máxima":"18.4(28)","temperatura_media_minima_mensual":6.0,"temperatura_media_maxima_mensual":15.1,"temperatura_max_absoluta_mes":"21.8(23)","temperatura_min_absoluta_mes":"-1.8(18)","temperatura_minima_mas_baja":13.5,"tempetatura_mas_baja_mes":11.0,"dias_con_precipitacion_mayor_01":19.0,"dias_con_precipitacion_mayor_0100":7.0,"dias_con_precipitacion_mayor_10":1.0,"dias_con_precipitacion_mayor_30":0.0,"tension_vapor_media":105,"precipitacion_total_mes":50.2,"dias_temperatura_menor_0":3,"temperatura_media_mes":10.6,"indice_evaporacion":0.1308926563,"mes":2,"indice_solar":0.4,"sequia_meteorologica":0.0,"sequia_agrícola":0.0}
{"id_estacion":"1465U","fecha":1583020800000,"precipitación_máxima":"28.8(01)","temperatura_media_minima_mensual":4.6,"temperatura_media_maxima_mensual":14.9,"temperatura_max_absoluta_mes":"21.5(18)","temperatura_min_absoluta_mes":"-1.1(27)","temperatura_minima_mas_baja":11.8,"tempetatura_mas_baja_mes":7.4,"dias_con_precipitacion_mayor_01":21.0,"dias_con_precipitacion_mayor_0100":11.0,"dias_con_precipitacion_mayor_10":4.0,"dias_con_precipitacion_mayor_30":0.0,"tension_vapor_media":101,"precipitacion_total_mes":127.6,"dias_temperatura_menor_0":1,"temperatura_media_mes":9.8,"indice_evaporacion":0.0199056255,"mes":3,"indice_solar":0.5,"sequia_meteorologica":0.4702,"sequia_agrícola":0.4653009437}
{"id_estacion":"1465U","fecha":1585699200000,"precipitación_máxima":"28.4(05)","temperatura_media_minima_mensual":8.0,"temperatura_media_maxima_mensual":15.8,"temperatura_max_absoluta_mes":"20.6(24)","temperatura_min_absoluta_mes":"1.1(03)","temperatura_minima_mas_baja":11.7,"tempetatura_mas_baja_mes":12.1,"dias_con_precipitacion_mayor_01":25.0,"dias_con_precipitacion_mayor_0100":18.0,"dias_con_precipitacion_mayor_10":4.0,"dias_con_precipitacion_mayor_30":0.0,"tension_vapor_media":121,"precipitacion_total_mes":107.8,"dias_temperatura_menor_0":0,"temperatura_media_mes":11.9,"indice_evaporacion":0.0501693481,"mes":4,"indice_solar":0.6,"sequia_meteorologica":0.2722,"sequia_agrícola":0.2659983065}
{"id_estacion":"1465U","fecha":1588291200000,"precipitación_máxima":"35.2(13)","temperatura_media_minima_mensual":9.8,"temperatura_media_maxima_mensual":22.8,"temperatura_max_absoluta_mes":"31.7(28)","temperatura_min_absoluta_mes":"4.3(16)","temperatura_minima_mas_baja":14.6,"tempetatura_mas_baja_mes":14.1,"dias_con_precipitacion_mayor_01":12.0,"dias_con_precipitacion_mayor_0100":6.0,"dias_con_precipitacion_mayor_10":2.0,"dias_con_precipitacion_mayor_30":1.0,"tension_vapor_media":146,"precipitacion_total_mes":58.6,"dias_temperatura_menor_0":0,"temperatura_media_mes":16.4,"indice_evaporacion":0.1786462153,"mes":5,"indice_solar":0.7,"sequia_meteorologica":0.0,"sequia_agrícola":0.0}
{"id_estacion":"1465U","fecha":1590969600000,"precipitación_máxima":"15.4(12)","temperatura_media_minima_mensual":10.7,"temperatura_media_maxima_mensual":21.2,"temperatura_max_absoluta_mes":"33.2(23)","temperatura_min_absoluta_mes":"4.0(08)","temperatura_minima_mas_baja":15.2,"tempetatura_mas_baja_mes":15.1,"dias_con_precipitacion_mayor_01":11.0,"dias_con_precipitacion_mayor_0100":5.0,"dias_con_precipitacion_mayor_10":1.0,"dias_con_precipitacion_mayor_30":0.0,"tension_vapor_media":149,"precipitacion_total_mes":31.2,"dias_temperatura_menor_0":0,"temperatura_media_mes":16.0,"indice_evaporacion":0.3082703648,"mes":6,"indice_solar":0.9,"sequia_meteorologica":0.0,"sequia_agrícola":0.0}
{"id_estacion":"1465U","fecha":1593561600000,"precipitación_máxima":"0.2(01)","temperatura_media_minima_mensual":13.0,"temperatura_media_maxima_mensual":28.3,"temperatura_max_absoluta_mes":"34.5(18)","temperatura_min_absoluta_mes":"4.6(03)","temperatura_minima_mas_baja":16.8,"tempetatura_mas_baja_mes":19.4,"dias_con_precipitacion_mayor_01":2.0,"dias_con_precipitacion_mayor_0100":0.0,"dias_con_precipitacion_mayor_10":0.0,"dias_con_precipitacion_mayor_30":0.0,"tension_vapor_media":170,"precipitacion_total_mes":0.4,"dias_temperatura_menor_0":0,"temperatura_media_mes":20.7,"indice_evaporacion":1.0,"mes":7,"indice_solar":1.0,"sequia_meteorologica":0.0,"sequia_agrícola":0.0}
{"id_estacion":"1465U","fecha":1596240000000,"precipitación_máxima":"19.2(17)","temperatura_media_minima_mensual":12.7,"temperatura_media_maxima_mensual":24.7,"temperatura_max_absoluta_mes":"33.7(06)","temperatura_min_absoluta_mes":"6.6(30)","temperatura_minima_mas_baja":17.2,"tempetatura_mas_baja_mes":18.8,"dias_con_precipitacion_mayor_01":17.0,"dias_con_precipitacion_mayor_0100":9.0,"dias_con_precipitacion_mayor_10":4.0,"dias_con_precipitacion_mayor_30":0.0,"tension_vapor_media":168,"precipitacion_total_mes":78.4,"dias_temperatura_menor_0":0,"temperatura_media_mes":18.7,"indice_evaporacion":0.1505468126,"mes":8,"indice_solar":0.9,"sequia_meteorologica":0.0,"sequia_agrícola":0.0}
{"id_estacion":"1465U","fecha":1598918400000,"precipitación_máxima":null,"temperatura_media_minima_mensual":10.9,"temperatura_media_maxima_mensual":24.2,"temperatura_max_absoluta_mes":"34.2(12)","temperatura_min_absoluta_mes":"3.1(28)","temperatura_minima_mas_baja":16.2,"tempetatura_mas_baja_mes":15.6,"dias_con_precipitacion_mayor_01":null,"dias_con_precipitacion_mayor_0100":null,"dias_con_precipitacion_mayor_10":null,"dias_con_precipitacion_mayor_30":null,"tension_vapor_media":150,"precipitacion_total_mes":null,"dias_temperatura_menor_0":0,"temperatura_media_mes":17.6,"indice_evaporacion":null,"mes":9,"indice_solar":0.7,"sequia_meteorologica":null,"sequia_agrícola":null}
