{"id_estacion":"8458X","fecha":"2023-10-01","precipitación_máxima":"17.2(19)","temperatura_media_minima_mensual":7.1,"temperatura_media_maxima_mensual":19.2,"temperatura_max_absoluta_mes":"28.5(01)","temperatura_min_absoluta_mes":"0.4(22)","temperatura_minima_mas_baja":12.8,"tempetatura_mas_baja_mes":10.7,"dias_con_precipitacion_mayor_01":7,"dias_con_precipitacion_mayor_0100":5,"dias_con_precipitacion_mayor_10":1,"dias_con_precipitacion_mayor_30":0,"tension_vapor_media":97,"precipitacion_total_mes":25.4,"dias_temperatura_menor_0":0,"temperatura_media_mes":13.2,"indice_evaporacion":0.3383826551,"mes":10,"indice_solar":0.5,"sequia_meteorologica":0.0,"sequia_agrícola":0.0}
{"id_estacion":"8458X","fecha":"2023-11-01","precipitación_máxima":"11.0(02)","temperatura_media_minima_mensual":2.4,"temperatura_media_maxima_mensual":13.0,"temperatura_max_absoluta_mes":"21.5(19)","temperatura_min_absoluta_mes":"-4.4(23)","temperatura_minima_mas_baja":7.7,"tempetatura_mas_baja_mes":6.5,"dias_con_precipitacion_mayor_01":9,"dias_con_precipitacion_mayor_0100":4,"dias_con_precipitacion_mayor_10":1,"dias_con_precipitacion_mayor_30":0,"tension_vapor_media":75,"precipitacion_total_mes":20.6,"dias_temperatura_menor_0":7,"temperatura_media_mes":7.7,"indice_evaporacion":0.2453027868,"mes":11,"indice_solar":0.3,"sequia_meteorologica":0.0,"sequia_agrícola":0.0}
{"id_estacion":"8458X","fecha":"2023-12-01","precipitación_máxima":"10.6(07)","temperatura_media_minima_mensual":-1.2,"temperatura_media_maxima_mensual":10.2,"temperatura_max_absoluta_mes":"18.0(11)","temperatura_min_absoluta_mes":"-6.8(18)","temperatura_minima_mas_baja":6.9,"tempetatura_mas_baja_mes":4.1,"dias_con_precipitacion_mayor_01":6,"dias_con_precipitacion_mayor_0100":3,"dias_con_precipitacion_mayor_10":1,"dias_con_precipitacion_mayor_30":0,"tension_vapor_media":53,"precipitacion_total_mes":14.8,"dias_temperatura_menor_0":20,"temperatura_media_mes":4.5,"indice_evaporacion":0.1934589555,"mes":12,"indice_solar":0.2,"sequia_meteorologica":0.0,"sequia_agrícola":0.0}
{"id_estacion":"8458X","fecha":"2023-01-01","precipitación_máxima":"14.0(08)","temperatura_media_minima_mensual":-3.2,"temperatura_media_maxima_mensual":6.4,"temperatura_max_absoluta_mes":"14.7(01)","temperatura_min_absoluta_mes":"-10.4(30)","temperatura_minima_mas_baja":5.1,"tempetatura_mas_baja_mes":-2.2,"dias_con_precipitacion_mayor_01":7,"dias_con_precipitacion_mayor_0100":2,"dias_con_precipitacion_mayor_10":1,"dias_con_precipitacion_mayor_30":0,"tension_vapor_media":48,"precipitacion_total_mes":16.6,"dias_temperatura_menor_0":26,"temperatura_media_mes":1.6,"indice_evaporacion":0.0,"mes":1,"indice_solar":0.3,"sequia_meteorologica":0.0,"sequia_agrícola":0.0}
{"id_estacion":"8458X","fecha":"2023-02-01","precipitación_máxima":"1.4(23)","temperatura_media_minima_mensual":-5.1,"temperatura_media_maxima_mensual":8.2,"temperatura_max_absoluta_mes":"16.5(19)","temperatura_min_absoluta_mes":"-9.4(12)","temperatura_minima_mas_baja":0.9,"tempetatura_mas_baja_mes":-3.7,"dias_con_precipitacion_mayor_01":6,"dias_con_precipitacion_mayor_0100":2,"dias_con_precipitacion_mayor_10":0,"dias_con_precipitacion_mayor_30":0,"tension_vapor_media":43,"precipitacion_total_mes":3.4,"dias_temperatura_menor_0":27,"temperatura_media_mes":1.6,"indice_evaporacion":0.3091211443,"mes":2,"indice_solar":0.4,"sequia_meteorologica":0.0,"sequia_agrícola":0.0}
{"id_estacion":"8458X","fecha":"2023-03-01","precipitación_máxima":"5.0(09)","temperatura_media_minima_mensual":0.7,"temperatura_media_maxima_mensual":14.3,"temperatura_max_absoluta_mes":"22.0(29)","temperatura_min_absoluta_mes":"-8.3(01)","temperatura_minima_mas_baja":7.7,"tempetatura_mas_baja_mes":0.6,"dias_con_precipitacion_mayor_01":2,"dias_con_precipitacion_mayor_0100":1,"dias_con_precipitacion_mayor_10":0,"dias_con_precipitacion_mayor_30":0,"tension_vapor_media":57,"precipitacion_total_mes":5.4,"dias_temperatura_menor_0":11,"temperatura_media_mes":7.5,"indice_evaporacion":0.6572784143,"mes":3,"indice_solar":0.5,"sequia_meteorologica":0.0,"sequia_agrícola":0.0}
{"id_estacion":"8458X","fecha":"2023-04-01","precipitación_máxima":"3.4(01)","temperatura_media_minima_mensual":2.0,"temperatura_media_maxima_mensual":18.3,"temperatura_max_absoluta_mes":"26.4(28)","temperatura_min_absoluta_mes":"-6.4(05)","temperatura_minima_mas_baja":9.1,"tempetatura_mas_baja_mes":9.2,"dias_con_precipitacion_mayor_01":5,"dias_con_precipitacion_mayor_0100":4,"dias_con_precipitacion_mayor_10":0,"dias_con_precipitacion_mayor_30":0,"tension_vapor_media":60,"precipitacion_total_mes":9.8,"dias_temperatura_menor_0":8,"temperatura_media_mes":10.1,"indice_evaporacion":0.5589063706,"mes":4,"indice_solar":0.6,"sequia_meteorologica":0.0,"sequia_agrícola":0.0}
{"id_estacion":"8458X","fecha":"2023-05-01","precipitación_máxima":"21.0(28)","temperatura_media_minima_mensual":4.1,"temperatura_media_maxima_mensual":17.3,"temperatura_max_absoluta_mes":"24.5(03)","temperatura_min_absoluta_mes":"-2.3(17)","temperatura_minima_mas_baja":9.1,"tempetatura_mas_baja_mes":10.8,"dias_con_precipitacion_mayor_01":12,"dias_con_precipitacion_mayor_0100":10,"dias_con_precipitacion_mayor_10":2,"dias_con_precipitacion_mayor_30":0,"tension_vapor_media":78,"precipitacion_total_mes":60.8,"dias_temperatura_menor_0":3,"temperatura_media_mes":10.7,"indice_evaporacion":0.0822303026,"mes":5,"indice_solar":0.7,"sequia_meteorologica":0.2863333333,"sequia_agrícola":0.2788110303}
{"id_estacion":"8458X","fecha":"2023-06-01","precipitación_máxima":"57.2(12)","temperatura_media_minima_mensual":10.2,"temperatura_media_maxima_mensual":22.3,"temperatura_max_absoluta_mes":"30.5(25)","temperatura_min_absoluta_mes":"4.5(03)","temperatura_minima_mas_baja":14.1,"tempetatura_mas_baja_mes":14.5,"dias_con_precipitacion_mayor_01":14,"dias_con_precipitacion_mayor_0100":11,"dias_con_precipitacion_mayor_10":3,"dias_con_precipitacion_mayor_30":1,"tension_vapor_media":135,"precipitacion_total_mes":132.4,"dias_temperatura_menor_0":0,"temperatura_media_mes":16.3,"indice_evaporacion":0.0289087759,"mes":6,"indice_solar":0.9,"sequia_meteorologica":1.0023333333,"sequia_agrícola":0.9933442456}
{"id_estacion":"8458X","fecha":"2023-07-01","precipitación_máxima":"12.6(03)","temperatura_media_minima_mensual":14.1,"temperatura_media_maxima_mensual":28.5,"temperatura_max_absoluta_mes":"34.9(18)","temperatura_min_absoluta_mes":"8.9(26)","temperatura_minima_mas_baja":19.5,"tempetatura_mas_baja_mes":22.5,"dias_con_precipitacion_mayor_01":4,"dias_con_precipitacion_mayor_0100":4,"dias_con_precipitacion_mayor_10":2,"dias_con_precipitacion_mayor_30":0,"tension_vapor_media":146,"precipitacion_total_mes":41.0,"dias_temperatura_menor_0":0,"temperatura_media_mes":21.3,"indice_evaporacion":0.3382830048,"mes":7,"indice_solar":1.0,"sequia_meteorologica":0.0883333333,"sequia_agrícola":0.0752505033}
{"id_estacion":"8458X","fecha":"2023-08-01","precipitación_máxima":"2.2(26)","temperatura_media_minima_mensual":12.7,"temperatura_media_maxima_mensual":28.8,"temperatura_max_absoluta_mes":"36.1(09)","temperatura_min_absoluta_mes":"6.2(31)","temperatura_minima_mas_baja":18.0,"tempetatura_mas_baja_mes":16.2,"dias_con_precipitacion_mayor_01":3,"dias_con_precipitacion_mayor_0100":2,"dias_con_precipitacion_mayor_10":0,"dias_con_precipitacion_mayor_30":0,"tension_vapor_media":116,"precipitacion_total_mes":4.0,"dias_temperatura_menor_0":0,"temperatura_media_mes":20.8,"indice_evaporacion":1.0,"mes":8,"indice_solar":0.9,"sequia_meteorologica":0.0,"sequia_agrícola":0.0}
{"id_estacion":"8458X","fecha":"2023-09-01","precipitación_máxima":"21.0(02)","temperatura_media_minima_mensual":10.0,"temperatura_media_maxima_mensual":22.8,"temperatura_max_absoluta_mes":"28.3(30)","temperatura_min_absoluta_mes":"4.3(23)","temperatura_minima_mas_baja":15.2,"tempetatura_mas_baja_mes":15.6,"dias_con_precipitacion_mayor_01":6,"dias_con_precipitacion_mayor_0100":4,"dias_con_precipitacion_mayor_10":2,"dias_con_precipitacion_mayor_30":0,"tension_vapor_media":128,"precipitacion_total_mes":51.8,"dias_temperatura_menor_0":0,"temperatura_media_mes":16.5,"indice_evaporacion":0.2046746629,"mes":9,"indice_solar":0.7,"sequia_meteorologica":0.1963333333,"sequia_agrícola":0.1875865867}
