[
    {
        "id_estacion":"9513X",
        "fecha":"2020-01-01",
        "precipitacion_maxima":null,
        "temperatura_media_minima_mensual":1.2,
        "temperatura_media_maxima_mensual":10.8,
        "temperatura_max_absoluta_mes":"15.5(31)",
        "temperatura_min_absoluta_mes":"-2.9(12)",
        "temperatura_minima_mas_baja":9.8,
        "tempetatura_mas_baja_mes":-0.8,
        "dias_con_precipitacion_mayor_01":null,
        "dias_con_precipitacion_mayor_0100":null,
        "dias_con_precipitacion_mayor_10":null,
        "dias_con_precipitacion_mayor_30":null,
        "tension_vapor_media":65,
        "precipitacion_total_mes":86.6,
        "dias_temperatura_menor_0":13,
        "temperatura_media_mes":6.0,
        "indice_evaporacion":0.0,
        "mes":1,
        "year":2020,
        "indice_solar":0.3,
        "sequia_meteorologica":0.3833333333,
        "sequia_agricola":0.3806333333,
        "nomb_estacion":"MUNIESA",
        "provincia":"TERUEL",
        "lat":41.0311111111,
        "long":-0.8055555556
    },
    {
        "id_estacion":"9513X",
        "fecha":"2020-02-01",
        "precipitacion_maxima":"0.0(--)",
        "temperatura_media_minima_mensual":4.6,
        "temperatura_media_maxima_mensual":16.2,
        "temperatura_max_absoluta_mes":"21.6(24)",
        "temperatura_min_absoluta_mes":"-0.9(19)",
        "temperatura_minima_mas_baja":9.9,
        "tempetatura_mas_baja_mes":10.2,
        "dias_con_precipitacion_mayor_01":0.0,
        "dias_con_precipitacion_mayor_0100":0.0,
        "dias_con_precipitacion_mayor_10":0.0,
        "dias_con_precipitacion_mayor_30":0.0,
        "tension_vapor_media":76,
        "precipitacion_total_mes":0.0,
        "dias_temperatura_menor_0":2,
        "temperatura_media_mes":10.4,
        "indice_evaporacion":1.0,
        "mes":2,
        "year":2020,
        "indice_solar":0.4,
        "sequia_meteorologica":0.0,
        "sequia_agricola":0.0,
        "nomb_estacion":"MUNIESA",
        "provincia":"TERUEL",
        "lat":41.0311111111,
        "long":-0.8055555556
    },
    {
        "id_estacion":"9513X",
        "fecha":"2020-03-01",
        "precipitacion_maxima":"34.6(16)",
        "temperatura_media_minima_mensual":3.5,
        "temperatura_media_maxima_mensual":13.5,
        "temperatura_max_absoluta_mes":"24.9(11)",
        "temperatura_min_absoluta_mes":"-2.0(27)",
        "temperatura_minima_mas_baja":9.0,
        "tempetatura_mas_baja_mes":4.3,
        "dias_con_precipitacion_mayor_01":13.0,
        "dias_con_precipitacion_mayor_0100":11.0,
        "dias_con_precipitacion_mayor_10":2.0,
        "dias_con_precipitacion_mayor_30":1.0,
        "tension_vapor_media":80,
        "precipitacion_total_mes":83.2,
        "dias_temperatura_menor_0":4,
        "temperatura_media_mes":8.5,
        "indice_evaporacion":0.0298317155,
        "mes":3,
        "year":2020,
        "indice_solar":0.5,
        "sequia_meteorologica":0.3493333333,
        "sequia_agricola":0.3443350162,
        "nomb_estacion":"MUNIESA",
        "provincia":"TERUEL",
        "lat":41.0311111111,
        "long":-0.8055555556
    },
    {
        "id_estacion":"9513X",
        "fecha":"2020-04-01",
        "precipitacion_maxima":"24.4(24)",
        "temperatura_media_minima_mensual":7.8,
        "temperatura_media_maxima_mensual":16.3,
        "temperatura_max_absoluta_mes":"20.6(16)",
        "temperatura_min_absoluta_mes":"1.5(03)",
        "temperatura_minima_mas_baja":12.0,
        "tempetatura_mas_baja_mes":8.8,
        "dias_con_precipitacion_mayor_01":16.0,
        "dias_con_precipitacion_mayor_0100":9.0,
        "dias_con_precipitacion_mayor_10":2.0,
        "dias_con_precipitacion_mayor_30":0.0,
        "tension_vapor_media":109,
        "precipitacion_total_mes":75.6,
        "dias_temperatura_menor_0":0,
        "temperatura_media_mes":12.1,
        "indice_evaporacion":0.0782455062,
        "mes":4,
        "year":2020,
        "indice_solar":0.6,
        "sequia_meteorologica":0.2733333333,
        "sequia_agricola":0.2668508783,
        "nomb_estacion":"MUNIESA",
        "provincia":"TERUEL",
        "lat":41.0311111111,
        "long":-0.8055555556
    },
    {
        "id_estacion":"9513X",
        "fecha":"2020-05-01",
        "precipitacion_maxima":"38.8(09)",
        "temperatura_media_minima_mensual":10.7,
        "temperatura_media_maxima_mensual":22.5,
        "temperatura_max_absoluta_mes":"29.1(22)",
        "temperatura_min_absoluta_mes":"6.6(18)",
        "temperatura_minima_mas_baja":15.2,
        "tempetatura_mas_baja_mes":13.4,
        "dias_con_precipitacion_mayor_01":11.0,
        "dias_con_precipitacion_mayor_0100":9.0,
        "dias_con_precipitacion_mayor_10":6.0,
        "dias_con_precipitacion_mayor_30":1.0,
        "tension_vapor_media":131,
        "precipitacion_total_mes":129.2,
        "dias_temperatura_menor_0":0,
        "temperatura_media_mes":16.7,
        "indice_evaporacion":0.0531083387,
        "mes":5,
        "year":2020,
        "indice_solar":0.7,
        "sequia_meteorologica":0.8093333333,
        "sequia_agricola":0.8021022499,
        "nomb_estacion":"MUNIESA",
        "provincia":"TERUEL",
        "lat":41.0311111111,
        "long":-0.8055555556
    },
    {
        "id_estacion":"9513X",
        "fecha":"2020-06-01",
        "precipitacion_maxima":"22.0(26)",
        "temperatura_media_minima_mensual":12.6,
        "temperatura_media_maxima_mensual":24.8,
        "temperatura_max_absoluta_mes":"30.9(23)",
        "temperatura_min_absoluta_mes":"6.7(08)",
        "temperatura_minima_mas_baja":16.6,
        "tempetatura_mas_baja_mes":17.1,
        "dias_con_precipitacion_mayor_01":9.0,
        "dias_con_precipitacion_mayor_0100":8.0,
        "dias_con_precipitacion_mayor_10":3.0,
        "dias_con_precipitacion_mayor_30":0.0,
        "tension_vapor_media":137,
        "precipitacion_total_mes":72.6,
        "dias_temperatura_menor_0":0,
        "temperatura_media_mes":18.7,
        "indice_evaporacion":0.1497260608,
        "mes":6,
        "year":2020,
        "indice_solar":0.9,
        "sequia_meteorologica":0.2433333333,
        "sequia_agricola":0.2331360727,
        "nomb_estacion":"MUNIESA",
        "provincia":"TERUEL",
        "lat":41.0311111111,
        "long":-0.8055555556
    },
    {
        "id_estacion":"9513X",
        "fecha":"2020-07-01",
        "precipitacion_maxima":"7.2(30)",
        "temperatura_media_minima_mensual":15.7,
        "temperatura_media_maxima_mensual":30.4,
        "temperatura_max_absoluta_mes":"36.1(31)",
        "temperatura_min_absoluta_mes":"10.8(04)",
        "temperatura_minima_mas_baja":19.8,
        "tempetatura_mas_baja_mes":24.4,
        "dias_con_precipitacion_mayor_01":4.0,
        "dias_con_precipitacion_mayor_0100":2.0,
        "dias_con_precipitacion_mayor_10":0.0,
        "dias_con_precipitacion_mayor_30":0.0,
        "tension_vapor_media":144,
        "precipitacion_total_mes":10.6,
        "dias_temperatura_menor_0":0,
        "temperatura_media_mes":23.1,
        "indice_evaporacion":0.6636677942,
        "mes":7,
        "year":2020,
        "indice_solar":1.0,
        "sequia_meteorologica":0.0,
        "sequia_agricola":0.0,
        "nomb_estacion":"MUNIESA",
        "provincia":"TERUEL",
        "lat":41.0311111111,
        "long":-0.8055555556
    },
    {
        "id_estacion":"9513X",
        "fecha":"2020-08-01",
        "precipitacion_maxima":"7.4(09)",
        "temperatura_media_minima_mensual":15.9,
        "temperatura_media_maxima_mensual":30.1,
        "temperatura_max_absoluta_mes":"36.5(20)",
        "temperatura_min_absoluta_mes":"9.3(31)",
        "temperatura_minima_mas_baja":21.3,
        "tempetatura_mas_baja_mes":20.4,
        "dias_con_precipitacion_mayor_01":5.0,
        "dias_con_precipitacion_mayor_0100":4.0,
        "dias_con_precipitacion_mayor_10":0.0,
        "dias_con_precipitacion_mayor_30":0.0,
        "tension_vapor_media":142,
        "precipitacion_total_mes":13.4,
        "dias_temperatura_menor_0":0,
        "temperatura_media_mes":23.0,
        "indice_evaporacion":0.6063629005,
        "mes":8,
        "year":2020,
        "indice_solar":0.9,
        "sequia_meteorologica":0.0,
        "sequia_agricola":0.0,
        "nomb_estacion":"MUNIESA",
        "provincia":"TERUEL",
        "lat":41.0311111111,
        "long":-0.8055555556
    },
    {
        "id_estacion":"9513X",
        "fecha":"2020-09-01",
        "precipitacion_maxima":"3.4(18)",
        "temperatura_media_minima_mensual":12.2,
        "temperatura_media_maxima_mensual":24.6,
        "temperatura_max_absoluta_mes":"30.7(13)",
        "temperatura_min_absoluta_mes":"4.9(29)",
        "temperatura_minima_mas_baja":17.6,
        "tempetatura_mas_baja_mes":14.9,
        "dias_con_precipitacion_mayor_01":6.0,
        "dias_con_precipitacion_mayor_0100":4.0,
        "dias_con_precipitacion_mayor_10":0.0,
        "dias_con_precipitacion_mayor_30":0.0,
        "tension_vapor_media":115,
        "precipitacion_total_mes":10.0,
        "dias_temperatura_menor_0":0,
        "temperatura_media_mes":18.4,
        "indice_evaporacion":0.6234919265,
        "mes":9,
        "year":2020,
        "indice_solar":0.7,
        "sequia_meteorologica":0.0,
        "sequia_agricola":0.0,
        "nomb_estacion":"MUNIESA",
        "provincia":"TERUEL",
        "lat":41.0311111111,
        "long":-0.8055555556
    },
    {
        "id_estacion":"9513X",
        "fecha":"2020-10-01",
        "precipitacion_maxima":"10.6(02)",
        "temperatura_media_minima_mensual":8.0,
        "temperatura_media_maxima_mensual":18.7,
        "temperatura_max_absoluta_mes":"25.0(08)",
        "temperatura_min_absoluta_mes":"2.9(17)",
        "temperatura_minima_mas_baja":13.9,
        "tempetatura_mas_baja_mes":11.6,
        "dias_con_precipitacion_mayor_01":5.0,
        "dias_con_precipitacion_mayor_0100":2.0,
        "dias_con_precipitacion_mayor_10":1.0,
        "dias_con_precipitacion_mayor_30":0.0,
        "tension_vapor_media":91,
        "precipitacion_total_mes":14.6,
        "dias_temperatura_menor_0":0,
        "temperatura_media_mes":13.4,
        "indice_evaporacion":0.442445014,
        "mes":10,
        "year":2020,
        "indice_solar":0.5,
        "sequia_meteorologica":0.0,
        "sequia_agricola":0.0,
        "nomb_estacion":"MUNIESA",
        "provincia":"TERUEL",
        "lat":41.0311111111,
        "long":-0.8055555556
    },
    {
        "id_estacion":"9513X",
        "fecha":"2020-11-01",
        "precipitacion_maxima":"25.6(27)",
        "temperatura_media_minima_mensual":5.3,
        "temperatura_media_maxima_mensual":15.1,
        "temperatura_max_absoluta_mes":"24.5(02)",
        "temperatura_min_absoluta_mes":"-0.7(22)",
        "temperatura_minima_mas_baja":10.1,
        "tempetatura_mas_baja_mes":6.2,
        "dias_con_precipitacion_mayor_01":9.0,
        "dias_con_precipitacion_mayor_0100":8.0,
        "dias_con_precipitacion_mayor_10":1.0,
        "dias_con_precipitacion_mayor_30":0.0,
        "tension_vapor_media":92,
        "precipitacion_total_mes":57.6,
        "dias_temperatura_menor_0":2,
        "temperatura_media_mes":10.3,
        "indice_evaporacion":0.0929196348,
        "mes":11,
        "year":2020,
        "indice_solar":0.3,
        "sequia_meteorologica":0.0933333333,
        "sequia_agricola":0.089704137,
        "nomb_estacion":"MUNIESA",
        "provincia":"TERUEL",
        "lat":41.0311111111,
        "long":-0.8055555556
    },
    {
        "id_estacion":"9513X",
        "fecha":"2020-12-01",
        "precipitacion_maxima":"11.6(11)",
        "temperatura_media_minima_mensual":2.5,
        "temperatura_media_maxima_mensual":10.3,
        "temperatura_max_absoluta_mes":"18.1(23)",
        "temperatura_min_absoluta_mes":"-3.1(27)",
        "temperatura_minima_mas_baja":8.9,
        "tempetatura_mas_baja_mes":4.0,
        "dias_con_precipitacion_mayor_01":10.0,
        "dias_con_precipitacion_mayor_0100":5.0,
        "dias_con_precipitacion_mayor_10":1.0,
        "dias_con_precipitacion_mayor_30":0.0,
        "tension_vapor_media":71,
        "precipitacion_total_mes":25.8,
        "dias_temperatura_menor_0":6,
        "temperatura_media_mes":6.4,
        "indice_evaporacion":0.1432445328,
        "mes":12,
        "year":2020,
        "indice_solar":0.2,
        "sequia_meteorologica":0.0,
        "sequia_agricola":0.0,
        "nomb_estacion":"MUNIESA",
        "provincia":"TERUEL",
        "lat":41.0311111111,
        "long":-0.8055555556
    },
    {
        "id_estacion":"9513X",
        "fecha":"2021-01-01",
        "precipitacion_maxima":null,
        "temperatura_media_minima_mensual":1.1,
        "temperatura_media_maxima_mensual":8.4,
        "temperatura_max_absoluta_mes":"20.0(28)",
        "temperatura_min_absoluta_mes":"-7.1(12)",
        "temperatura_minima_mas_baja":10.8,
        "tempetatura_mas_baja_mes":-1.2,
        "dias_con_precipitacion_mayor_01":null,
        "dias_con_precipitacion_mayor_0100":null,
        "dias_con_precipitacion_mayor_10":null,
        "dias_con_precipitacion_mayor_30":null,
        "tension_vapor_media":62,
        "precipitacion_total_mes":36.6,
        "dias_temperatura_menor_0":13,
        "temperatura_media_mes":4.8,
        "indice_evaporacion":0.0168196717,
        "mes":1,
        "year":2021,
        "indice_solar":0.3,
        "sequia_meteorologica":0.0,
        "sequia_agricola":0.0,
        "nomb_estacion":"MUNIESA",
        "provincia":"TERUEL",
        "lat":41.0311111111,
        "long":-0.8055555556
    },
    {
        "id_estacion":"9513X",
        "fecha":"2021-02-01",
        "precipitacion_maxima":"12.2(21)",
        "temperatura_media_minima_mensual":4.4,
        "temperatura_media_maxima_mensual":14.1,
        "temperatura_max_absoluta_mes":"20.9(20)",
        "temperatura_min_absoluta_mes":"0.1(15)",
        "temperatura_minima_mas_baja":9.1,
        "tempetatura_mas_baja_mes":8.2,
        "dias_con_precipitacion_mayor_01":8.0,
        "dias_con_precipitacion_mayor_0100":4.0,
        "dias_con_precipitacion_mayor_10":1.0,
        "dias_con_precipitacion_mayor_30":0.0,
        "tension_vapor_media":80,
        "precipitacion_total_mes":25.6,
        "dias_temperatura_menor_0":0,
        "temperatura_media_mes":9.2,
        "indice_evaporacion":0.2952799149,
        "mes":2,
        "year":2021,
        "indice_solar":0.4,
        "sequia_meteorologica":0.0,
        "sequia_agricola":0.0,
        "nomb_estacion":"MUNIESA",
        "provincia":"TERUEL",
        "lat":41.0311111111,
        "long":-0.8055555556
    },
    {
        "id_estacion":"9513X",
        "fecha":"2021-03-01",
        "precipitacion_maxima":"5.4(19)",
        "temperatura_media_minima_mensual":3.1,
        "temperatura_media_maxima_mensual":13.6,
        "temperatura_max_absoluta_mes":"21.2(30)",
        "temperatura_min_absoluta_mes":"-2.5(10)",
        "temperatura_minima_mas_baja":7.7,
        "tempetatura_mas_baja_mes":6.9,
        "dias_con_precipitacion_mayor_01":3.0,
        "dias_con_precipitacion_mayor_0100":2.0,
        "dias_con_precipitacion_mayor_10":0.0,
        "dias_con_precipitacion_mayor_30":0.0,
        "tension_vapor_media":72,
        "precipitacion_total_mes":7.6,
        "dias_temperatura_menor_0":3,
        "temperatura_media_mes":8.4,
        "indice_evaporacion":0.7842492239,
        "mes":3,
        "year":2021,
        "indice_solar":0.5,
        "sequia_meteorologica":0.0,
        "sequia_agricola":0.0,
        "nomb_estacion":"MUNIESA",
        "provincia":"TERUEL",
        "lat":41.0311111111,
        "long":-0.8055555556
    },
    {
        "id_estacion":"9513X",
        "fecha":"2021-04-01",
        "precipitacion_maxima":"15.6(10)",
        "temperatura_media_minima_mensual":4.9,
        "temperatura_media_maxima_mensual":15.1,
        "temperatura_max_absoluta_mes":"19.7(01)",
        "temperatura_min_absoluta_mes":"-0.5(07)",
        "temperatura_minima_mas_baja":8.9,
        "tempetatura_mas_baja_mes":9.8,
        "dias_con_precipitacion_mayor_01":15.0,
        "dias_con_precipitacion_mayor_0100":12.0,
        "dias_con_precipitacion_mayor_10":3.0,
        "dias_con_precipitacion_mayor_30":0.0,
        "tension_vapor_media":88,
        "precipitacion_total_mes":78.4,
        "dias_temperatura_menor_0":1,
        "temperatura_media_mes":10.0,
        "indice_evaporacion":0.0115293909,
        "mes":4,
        "year":2021,
        "indice_solar":0.6,
        "sequia_meteorologica":0.401,
        "sequia_agricola":0.3951847061,
        "nomb_estacion":"MUNIESA",
        "provincia":"TERUEL",
        "lat":41.0311111111,
        "long":-0.8055555556
    },
    {
        "id_estacion":"9513X",
        "fecha":"2021-05-01",
        "precipitacion_maxima":"14.6(29)",
        "temperatura_media_minima_mensual":8.8,
        "temperatura_media_maxima_mensual":21.1,
        "temperatura_max_absoluta_mes":"28.2(21)",
        "temperatura_min_absoluta_mes":"5.0(02)",
        "temperatura_minima_mas_baja":14.8,
        "tempetatura_mas_baja_mes":11.0,
        "dias_con_precipitacion_mayor_01":8.0,
        "dias_con_precipitacion_mayor_0100":5.0,
        "dias_con_precipitacion_mayor_10":2.0,
        "dias_con_precipitacion_mayor_30":0.0,
        "tension_vapor_media":106,
        "precipitacion_total_mes":37.6,
        "dias_temperatura_menor_0":0,
        "temperatura_media_mes":15.0,
        "indice_evaporacion":0.3343088214,
        "mes":5,
        "year":2021,
        "indice_solar":0.7,
        "sequia_meteorologica":0.0,
        "sequia_agricola":0.0,
        "nomb_estacion":"MUNIESA",
        "provincia":"TERUEL",
        "lat":41.0311111111,
        "long":-0.8055555556
    },
    {
        "id_estacion":"9513X",
        "fecha":"2021-06-01",
        "precipitacion_maxima":"12.8(05)",
        "temperatura_media_minima_mensual":13.0,
        "temperatura_media_maxima_mensual":25.6,
        "temperatura_max_absoluta_mes":"32.3(14)",
        "temperatura_min_absoluta_mes":"9.1(24)",
        "temperatura_minima_mas_baja":18.6,
        "tempetatura_mas_baja_mes":18.3,
        "dias_con_precipitacion_mayor_01":10.0,
        "dias_con_precipitacion_mayor_0100":8.0,
        "dias_con_precipitacion_mayor_10":3.0,
        "dias_con_precipitacion_mayor_30":0.0,
        "tension_vapor_media":140,
        "precipitacion_total_mes":70.6,
        "dias_temperatura_menor_0":0,
        "temperatura_media_mes":19.4,
        "indice_evaporacion":0.2037037534,
        "mes":6,
        "year":2021,
        "indice_solar":0.9,
        "sequia_meteorologica":0.323,
        "sequia_agricola":0.3122629625,
        "nomb_estacion":"MUNIESA",
        "provincia":"TERUEL",
        "lat":41.0311111111,
        "long":-0.8055555556
    },
    {
        "id_estacion":"9513X",
        "fecha":"2021-07-01",
        "precipitacion_maxima":"8.2(31)",
        "temperatura_media_minima_mensual":14.8,
        "temperatura_media_maxima_mensual":29.9,
        "temperatura_max_absoluta_mes":"37.8(23)",
        "temperatura_min_absoluta_mes":"10.0(13)",
        "temperatura_minima_mas_baja":24.0,
        "tempetatura_mas_baja_mes":21.2,
        "dias_con_precipitacion_mayor_01":5.0,
        "dias_con_precipitacion_mayor_0100":4.0,
        "dias_con_precipitacion_mayor_10":0.0,
        "dias_con_precipitacion_mayor_30":0.0,
        "tension_vapor_media":138,
        "precipitacion_total_mes":12.6,
        "dias_temperatura_menor_0":0,
        "temperatura_media_mes":22.4,
        "indice_evaporacion":1.0,
        "mes":7,
        "year":2021,
        "indice_solar":1.0,
        "sequia_meteorologica":0.0,
        "sequia_agricola":0.0,
        "nomb_estacion":"MUNIESA",
        "provincia":"TERUEL",
        "lat":41.0311111111,
        "long":-0.8055555556
    },
    {
        "id_estacion":"9513X",
        "fecha":"2021-08-01",
        "precipitacion_maxima":"15.6(11)",
        "temperatura_media_minima_mensual":15.0,
        "temperatura_media_maxima_mensual":29.6,
        "temperatura_max_absoluta_mes":"39.1(14)",
        "temperatura_min_absoluta_mes":"10.4(18)",
        "temperatura_minima_mas_baja":22.7,
        "tempetatura_mas_baja_mes":21.9,
        "dias_con_precipitacion_mayor_01":3.0,
        "dias_con_precipitacion_mayor_0100":2.0,
        "dias_con_precipitacion_mayor_10":1.0,
        "dias_con_precipitacion_mayor_30":0.0,
        "tension_vapor_media":144,
        "precipitacion_total_mes":18.0,
        "dias_temperatura_menor_0":0,
        "temperatura_media_mes":22.3,
        "indice_evaporacion":0.8374365385,
        "mes":8,
        "year":2021,
        "indice_solar":0.9,
        "sequia_meteorologica":0.0,
        "sequia_agricola":0.0,
        "nomb_estacion":"MUNIESA",
        "provincia":"TERUEL",
        "lat":41.0311111111,
        "long":-0.8055555556
    },
    {
        "id_estacion":"9513X",
        "fecha":"2021-09-01",
        "precipitacion_maxima":"50.4(01)",
        "temperatura_media_minima_mensual":13.5,
        "temperatura_media_maxima_mensual":24.1,
        "temperatura_max_absoluta_mes":"30.1(06)",
        "temperatura_min_absoluta_mes":"8.0(22)",
        "temperatura_minima_mas_baja":19.0,
        "tempetatura_mas_baja_mes":18.1,
        "dias_con_precipitacion_mayor_01":5.0,
        "dias_con_precipitacion_mayor_0100":5.0,
        "dias_con_precipitacion_mayor_10":2.0,
        "dias_con_precipitacion_mayor_30":1.0,
        "tension_vapor_media":147,
        "precipitacion_total_mes":83.4,
        "dias_temperatura_menor_0":0,
        "temperatura_media_mes":18.8,
        "indice_evaporacion":0.1444145463,
        "mes":9,
        "year":2021,
        "indice_solar":0.7,
        "sequia_meteorologica":0.451,
        "sequia_agricola":0.4428558545,
        "nomb_estacion":"MUNIESA",
        "provincia":"TERUEL",
        "lat":41.0311111111,
        "long":-0.8055555556
    },
    {
        "id_estacion":"9513X",
        "fecha":"2021-10-01",
        "precipitacion_maxima":"12.8(03)",
        "temperatura_media_minima_mensual":7.9,
        "temperatura_media_maxima_mensual":20.2,
        "temperatura_max_absoluta_mes":"27.1(02)",
        "temperatura_min_absoluta_mes":"3.4(23)",
        "temperatura_minima_mas_baja":12.5,
        "tempetatura_mas_baja_mes":16.5,
        "dias_con_precipitacion_mayor_01":4.0,
        "dias_con_precipitacion_mayor_0100":3.0,
        "dias_con_precipitacion_mayor_10":1.0,
        "dias_con_precipitacion_mayor_30":0.0,
        "tension_vapor_media":102,
        "precipitacion_total_mes":24.0,
        "dias_temperatura_menor_0":0,
        "temperatura_media_mes":14.1,
        "indice_evaporacion":0.4936032239,
        "mes":10,
        "year":2021,
        "indice_solar":0.5,
        "sequia_meteorologica":0.0,
        "sequia_agricola":0.0,
        "nomb_estacion":"MUNIESA",
        "provincia":"TERUEL",
        "lat":41.0311111111,
        "long":-0.8055555556
    },
    {
        "id_estacion":"9513X",
        "fecha":"2021-11-01",
        "precipitacion_maxima":"18.4(23)",
        "temperatura_media_minima_mensual":3.1,
        "temperatura_media_maxima_mensual":10.6,
        "temperatura_max_absoluta_mes":"15.9(10)",
        "temperatura_min_absoluta_mes":"0.2(18)",
        "temperatura_minima_mas_baja":8.2,
        "tempetatura_mas_baja_mes":3.9,
        "dias_con_precipitacion_mayor_01":13.0,
        "dias_con_precipitacion_mayor_0100":7.0,
        "dias_con_precipitacion_mayor_10":3.0,
        "dias_con_precipitacion_mayor_30":0.0,
        "tension_vapor_media":75,
        "precipitacion_total_mes":57.6,
        "dias_temperatura_menor_0":0,
        "temperatura_media_mes":6.9,
        "indice_evaporacion":0.0,
        "mes":11,
        "year":2021,
        "indice_solar":0.3,
        "sequia_meteorologica":0.193,
        "sequia_agricola":0.1903,
        "nomb_estacion":"MUNIESA",
        "provincia":"TERUEL",
        "lat":41.0311111111,
        "long":-0.8055555556
    },
    {
        "id_estacion":"9513X",
        "fecha":"2021-12-01",
        "precipitacion_maxima":"2.2(01)",
        "temperatura_media_minima_mensual":3.3,
        "temperatura_media_maxima_mensual":13.1,
        "temperatura_max_absoluta_mes":"21.0(31)",
        "temperatura_min_absoluta_mes":"-5.0(18)",
        "temperatura_minima_mas_baja":11.0,
        "tempetatura_mas_baja_mes":5.9,
        "dias_con_precipitacion_mayor_01":8.0,
        "dias_con_precipitacion_mayor_0100":4.0,
        "dias_con_precipitacion_mayor_10":0.0,
        "dias_con_precipitacion_mayor_30":0.0,
        "tension_vapor_media":78,
        "precipitacion_total_mes":7.6,
        "dias_temperatura_menor_0":6,
        "temperatura_media_mes":8.2,
        "indice_evaporacion":0.7729689272,
        "mes":12,
        "year":2021,
        "indice_solar":0.2,
        "sequia_meteorologica":0.0,
        "sequia_agricola":0.0,
        "nomb_estacion":"MUNIESA",
        "provincia":"TERUEL",
        "lat":41.0311111111,
        "long":-0.8055555556
    },
    {
        "id_estacion":"9513X",
        "fecha":"2022-01-01",
        "precipitacion_maxima":"1.4(04)",
        "temperatura_media_minima_mensual":-0.4,
        "temperatura_media_maxima_mensual":11.6,
        "temperatura_max_absoluta_mes":"21.5(01)",
        "temperatura_min_absoluta_mes":"-6.4(22)",
        "temperatura_minima_mas_baja":8.1,
        "tempetatura_mas_baja_mes":5.5,
        "dias_con_precipitacion_mayor_01":1.0,
        "dias_con_precipitacion_mayor_0100":1.0,
        "dias_con_precipitacion_mayor_10":0.0,
        "dias_con_precipitacion_mayor_30":0.0,
        "tension_vapor_media":51,
        "precipitacion_total_mes":1.4,
        "dias_temperatura_menor_0":19,
        "temperatura_media_mes":5.6,
        "indice_evaporacion":0.9224122622,
        "mes":1,
        "year":2022,
        "indice_solar":0.3,
        "sequia_meteorologica":0.0,
        "sequia_agricola":0.0,
        "nomb_estacion":"MUNIESA",
        "provincia":"TERUEL",
        "lat":41.0311111111,
        "long":-0.8055555556
    },
    {
        "id_estacion":"9513X",
        "fecha":"2022-02-01",
        "precipitacion_maxima":"2.2(19)",
        "temperatura_media_minima_mensual":2.4,
        "temperatura_media_maxima_mensual":14.2,
        "temperatura_max_absoluta_mes":"22.3(18)",
        "temperatura_min_absoluta_mes":"-3.5(06)",
        "temperatura_minima_mas_baja":6.8,
        "tempetatura_mas_baja_mes":7.5,
        "dias_con_precipitacion_mayor_01":2.0,
        "dias_con_precipitacion_mayor_0100":1.0,
        "dias_con_precipitacion_mayor_10":0.0,
        "dias_con_precipitacion_mayor_30":0.0,
        "tension_vapor_media":63,
        "precipitacion_total_mes":2.4,
        "dias_temperatura_menor_0":5,
        "temperatura_media_mes":8.3,
        "indice_evaporacion":0.890598654,
        "mes":2,
        "year":2022,
        "indice_solar":0.4,
        "sequia_meteorologica":0.0,
        "sequia_agricola":0.0,
        "nomb_estacion":"MUNIESA",
        "provincia":"TERUEL",
        "lat":41.0311111111,
        "long":-0.8055555556
    },
    {
        "id_estacion":"9513X",
        "fecha":"2022-03-01",
        "precipitacion_maxima":"11.6(03)",
        "temperatura_media_minima_mensual":4.1,
        "temperatura_media_maxima_mensual":11.0,
        "temperatura_max_absoluta_mes":"18.6(01)",
        "temperatura_min_absoluta_mes":"1.1(06)",
        "temperatura_minima_mas_baja":7.7,
        "tempetatura_mas_baja_mes":6.2,
        "dias_con_precipitacion_mayor_01":18.0,
        "dias_con_precipitacion_mayor_0100":12.0,
        "dias_con_precipitacion_mayor_10":2.0,
        "dias_con_precipitacion_mayor_30":0.0,
        "tension_vapor_media":83,
        "precipitacion_total_mes":72.0,
        "dias_temperatura_menor_0":0,
        "temperatura_media_mes":7.6,
        "indice_evaporacion":0.0,
        "mes":3,
        "year":2022,
        "indice_solar":0.5,
        "sequia_meteorologica":0.396,
        "sequia_agricola":0.3913,
        "nomb_estacion":"MUNIESA",
        "provincia":"TERUEL",
        "lat":41.0311111111,
        "long":-0.8055555556
    },
    {
        "id_estacion":"9513X",
        "fecha":"2022-04-01",
        "precipitacion_maxima":"31.2(19)",
        "temperatura_media_minima_mensual":5.2,
        "temperatura_media_maxima_mensual":15.5,
        "temperatura_max_absoluta_mes":"24.9(11)",
        "temperatura_min_absoluta_mes":"-3.6(04)",
        "temperatura_minima_mas_baja":10.8,
        "tempetatura_mas_baja_mes":5.3,
        "dias_con_precipitacion_mayor_01":8.0,
        "dias_con_precipitacion_mayor_0100":7.0,
        "dias_con_precipitacion_mayor_10":4.0,
        "dias_con_precipitacion_mayor_30":1.0,
        "tension_vapor_media":87,
        "precipitacion_total_mes":80.8,
        "dias_temperatura_menor_0":5,
        "temperatura_media_mes":10.4,
        "indice_evaporacion":0.0242971304,
        "mes":4,
        "year":2022,
        "indice_solar":0.6,
        "sequia_meteorologica":0.484,
        "sequia_agricola":0.4780570287,
        "nomb_estacion":"MUNIESA",
        "provincia":"TERUEL",
        "lat":41.0311111111,
        "long":-0.8055555556
    },
    {
        "id_estacion":"9513X",
        "fecha":"2022-05-01",
        "precipitacion_maxima":"14.2(02)",
        "temperatura_media_minima_mensual":11.1,
        "temperatura_media_maxima_mensual":24.2,
        "temperatura_max_absoluta_mes":"33.3(21)",
        "temperatura_min_absoluta_mes":"6.4(07)",
        "temperatura_minima_mas_baja":18.7,
        "tempetatura_mas_baja_mes":12.3,
        "dias_con_precipitacion_mayor_01":9.0,
        "dias_con_precipitacion_mayor_0100":6.0,
        "dias_con_precipitacion_mayor_10":1.0,
        "dias_con_precipitacion_mayor_30":0.0,
        "tension_vapor_media":117,
        "precipitacion_total_mes":41.2,
        "dias_temperatura_menor_0":0,
        "temperatura_media_mes":17.6,
        "indice_evaporacion":0.2668856007,
        "mes":5,
        "year":2022,
        "indice_solar":0.7,
        "sequia_meteorologica":0.088,
        "sequia_agricola":0.078631144,
        "nomb_estacion":"MUNIESA",
        "provincia":"TERUEL",
        "lat":41.0311111111,
        "long":-0.8055555556
    },
    {
        "id_estacion":"9513X",
        "fecha":"2022-06-01",
        "precipitacion_maxima":"1.2(01)",
        "temperatura_media_minima_mensual":15.7,
        "temperatura_media_maxima_mensual":30.5,
        "temperatura_max_absoluta_mes":"38.0(18)",
        "temperatura_min_absoluta_mes":"8.5(28)",
        "temperatura_minima_mas_baja":25.2,
        "tempetatura_mas_baja_mes":21.8,
        "dias_con_precipitacion_mayor_01":5.0,
        "dias_con_precipitacion_mayor_0100":3.0,
        "dias_con_precipitacion_mayor_10":0.0,
        "dias_con_precipitacion_mayor_30":0.0,
        "tension_vapor_media":121,
        "precipitacion_total_mes":3.8,
        "dias_temperatura_menor_0":0,
        "temperatura_media_mes":23.2,
        "indice_evaporacion":1.0,
        "mes":6,
        "year":2022,
        "indice_solar":0.9,
        "sequia_meteorologica":0.0,
        "sequia_agricola":0.0,
        "nomb_estacion":"MUNIESA",
        "provincia":"TERUEL",
        "lat":41.0311111111,
        "long":-0.8055555556
    },
    {
        "id_estacion":"9513X",
        "fecha":"2022-07-01",
        "precipitacion_maxima":"27.0(06)",
        "temperatura_media_minima_mensual":17.4,
        "temperatura_media_maxima_mensual":32.1,
        "temperatura_max_absoluta_mes":"37.6(17)",
        "temperatura_min_absoluta_mes":"12.7(01)",
        "temperatura_minima_mas_baja":22.8,
        "tempetatura_mas_baja_mes":18.4,
        "dias_con_precipitacion_mayor_01":4.0,
        "dias_con_precipitacion_mayor_0100":3.0,
        "dias_con_precipitacion_mayor_10":1.0,
        "dias_con_precipitacion_mayor_30":0.0,
        "tension_vapor_media":151,
        "precipitacion_total_mes":34.0,
        "dias_temperatura_menor_0":0,
        "temperatura_media_mes":24.8,
        "indice_evaporacion":0.4272049435,
        "mes":7,
        "year":2022,
        "indice_solar":1.0,
        "sequia_meteorologica":0.016,
        "sequia_agricola":0.0020279506,
        "nomb_estacion":"MUNIESA",
        "provincia":"TERUEL",
        "lat":41.0311111111,
        "long":-0.8055555556
    },
    {
        "id_estacion":"9513X",
        "fecha":"2022-08-01",
        "precipitacion_maxima":"21.0(04)",
        "temperatura_media_minima_mensual":17.6,
        "temperatura_media_maxima_mensual":31.6,
        "temperatura_max_absoluta_mes":"36.5(12)",
        "temperatura_min_absoluta_mes":"12.8(27)",
        "temperatura_minima_mas_baja":23.2,
        "tempetatura_mas_baja_mes":22.9,
        "dias_con_precipitacion_mayor_01":10.0,
        "dias_con_precipitacion_mayor_0100":7.0,
        "dias_con_precipitacion_mayor_10":1.0,
        "dias_con_precipitacion_mayor_30":0.0,
        "tension_vapor_media":147,
        "precipitacion_total_mes":40.4,
        "dias_temperatura_menor_0":0,
        "temperatura_media_mes":24.6,
        "indice_evaporacion":0.3705039737,
        "mes":8,
        "year":2022,
        "indice_solar":0.9,
        "sequia_meteorologica":0.08,
        "sequia_agricola":0.0675949603,
        "nomb_estacion":"MUNIESA",
        "provincia":"TERUEL",
        "lat":41.0311111111,
        "long":-0.8055555556
    },
    {
        "id_estacion":"9513X",
        "fecha":"2022-09-01",
        "precipitacion_maxima":"17.6(23)",
        "temperatura_media_minima_mensual":13.1,
        "temperatura_media_maxima_mensual":25.6,
        "temperatura_max_absoluta_mes":"32.3(11)",
        "temperatura_min_absoluta_mes":"7.6(26)",
        "temperatura_minima_mas_baja":18.9,
        "tempetatura_mas_baja_mes":16.8,
        "dias_con_precipitacion_mayor_01":7.0,
        "dias_con_precipitacion_mayor_0100":3.0,
        "dias_con_precipitacion_mayor_10":1.0,
        "dias_con_precipitacion_mayor_30":0.0,
        "tension_vapor_media":126,
        "precipitacion_total_mes":29.8,
        "dias_temperatura_menor_0":0,
        "temperatura_media_mes":19.4,
        "indice_evaporacion":0.3912525535,
        "mes":9,
        "year":2022,
        "indice_solar":0.7,
        "sequia_meteorologica":0.0,
        "sequia_agricola":0.0,
        "nomb_estacion":"MUNIESA",
        "provincia":"TERUEL",
        "lat":41.0311111111,
        "long":-0.8055555556
    },
    {
        "id_estacion":"9513X",
        "fecha":"2022-10-01",
        "precipitacion_maxima":"6.6(10)",
        "temperatura_media_minima_mensual":12.4,
        "temperatura_media_maxima_mensual":24.3,
        "temperatura_max_absoluta_mes":"28.8(27)",
        "temperatura_min_absoluta_mes":"7.3(01)",
        "temperatura_minima_mas_baja":17.1,
        "tempetatura_mas_baja_mes":19.1,
        "dias_con_precipitacion_mayor_01":7.0,
        "dias_con_precipitacion_mayor_0100":2.0,
        "dias_con_precipitacion_mayor_10":0.0,
        "dias_con_precipitacion_mayor_30":0.0,
        "tension_vapor_media":113,
        "precipitacion_total_mes":13.6,
        "dias_temperatura_menor_0":0,
        "temperatura_media_mes":18.4,
        "indice_evaporacion":0.6278266807,
        "mes":10,
        "year":2022,
        "indice_solar":0.5,
        "sequia_meteorologica":0.0,
        "sequia_agricola":0.0,
        "nomb_estacion":"MUNIESA",
        "provincia":"TERUEL",
        "lat":41.0311111111,
        "long":-0.8055555556
    },
    {
        "id_estacion":"9513X",
        "fecha":"2022-11-01",
        "precipitacion_maxima":"21.0(11)",
        "temperatura_media_minima_mensual":6.3,
        "temperatura_media_maxima_mensual":15.3,
        "temperatura_max_absoluta_mes":"21.4(06)",
        "temperatura_min_absoluta_mes":"1.6(27)",
        "temperatura_minima_mas_baja":12.4,
        "tempetatura_mas_baja_mes":8.3,
        "dias_con_precipitacion_mayor_01":10.0,
        "dias_con_precipitacion_mayor_0100":5.0,
        "dias_con_precipitacion_mayor_10":1.0,
        "dias_con_precipitacion_mayor_30":0.0,
        "tension_vapor_media":91,
        "precipitacion_total_mes":37.8,
        "dias_temperatura_menor_0":0,
        "temperatura_media_mes":10.8,
        "indice_evaporacion":0.1659437818,
        "mes":11,
        "year":2022,
        "indice_solar":0.3,
        "sequia_meteorologica":0.054,
        "sequia_agricola":0.0496405622,
        "nomb_estacion":"MUNIESA",
        "provincia":"TERUEL",
        "lat":41.0311111111,
        "long":-0.8055555556
    },
    {
        "id_estacion":"9513X",
        "fecha":"2022-12-01",
        "precipitacion_maxima":"10.4(09)",
        "temperatura_media_minima_mensual":4.6,
        "temperatura_media_maxima_mensual":13.0,
        "temperatura_max_absoluta_mes":"20.5(24)",
        "temperatura_min_absoluta_mes":"-2.1(03)",
        "temperatura_minima_mas_baja":11.2,
        "tempetatura_mas_baja_mes":5.8,
        "dias_con_precipitacion_mayor_01":9.0,
        "dias_con_precipitacion_mayor_0100":7.0,
        "dias_con_precipitacion_mayor_10":1.0,
        "dias_con_precipitacion_mayor_30":0.0,
        "tension_vapor_media":84,
        "precipitacion_total_mes":31.6,
        "dias_temperatura_menor_0":4,
        "temperatura_media_mes":8.8,
        "indice_evaporacion":0.1601823856,
        "mes":12,
        "year":2022,
        "indice_solar":0.2,
        "sequia_meteorologica":0.0,
        "sequia_agricola":0.0,
        "nomb_estacion":"MUNIESA",
        "provincia":"TERUEL",
        "lat":41.0311111111,
        "long":-0.8055555556
    },
    {
        "id_estacion":"9513X",
        "fecha":"2023-01-01",
        "precipitacion_maxima":"1.6(02)",
        "temperatura_media_minima_mensual":0.9,
        "temperatura_media_maxima_mensual":9.6,
        "temperatura_max_absoluta_mes":"17.7(01)",
        "temperatura_min_absoluta_mes":"-5.8(30)",
        "temperatura_minima_mas_baja":11.1,
        "tempetatura_mas_baja_mes":1.6,
        "dias_con_precipitacion_mayor_01":6.0,
        "dias_con_precipitacion_mayor_0100":3.0,
        "dias_con_precipitacion_mayor_10":0.0,
        "dias_con_precipitacion_mayor_30":0.0,
        "tension_vapor_media":59,
        "precipitacion_total_mes":5.4,
        "dias_temperatura_menor_0":14,
        "temperatura_media_mes":5.3,
        "indice_evaporacion":0.4421663712,
        "mes":1,
        "year":2023,
        "indice_solar":0.3,
        "sequia_meteorologica":0.0,
        "sequia_agricola":0.0,
        "nomb_estacion":"MUNIESA",
        "provincia":"TERUEL",
        "lat":41.0311111111,
        "long":-0.8055555556
    },
    {
        "id_estacion":"9513X",
        "fecha":"2023-02-01",
        "precipitacion_maxima":null,
        "temperatura_media_minima_mensual":-0.6,
        "temperatura_media_maxima_mensual":10.5,
        "temperatura_max_absoluta_mes":"18.1(20)",
        "temperatura_min_absoluta_mes":"-4.9(27)",
        "temperatura_minima_mas_baja":6.7,
        "tempetatura_mas_baja_mes":1.4,
        "dias_con_precipitacion_mayor_01":null,
        "dias_con_precipitacion_mayor_0100":null,
        "dias_con_precipitacion_mayor_10":null,
        "dias_con_precipitacion_mayor_30":null,
        "tension_vapor_media":54,
        "precipitacion_total_mes":18.0,
        "dias_temperatura_menor_0":19,
        "temperatura_media_mes":5.0,
        "indice_evaporacion":0.0668259334,
        "mes":2,
        "year":2023,
        "indice_solar":0.4,
        "sequia_meteorologica":0.0,
        "sequia_agricola":0.0,
        "nomb_estacion":"MUNIESA",
        "provincia":"TERUEL",
        "lat":41.0311111111,
        "long":-0.8055555556
    },
    {
        "id_estacion":"9513X",
        "fecha":"2023-03-01",
        "precipitacion_maxima":"1.2(09)",
        "temperatura_media_minima_mensual":5.7,
        "temperatura_media_maxima_mensual":18.1,
        "temperatura_max_absoluta_mes":"26.2(13)",
        "temperatura_min_absoluta_mes":"-4.1(01)",
        "temperatura_minima_mas_baja":13.0,
        "tempetatura_mas_baja_mes":3.5,
        "dias_con_precipitacion_mayor_01":1.0,
        "dias_con_precipitacion_mayor_0100":1.0,
        "dias_con_precipitacion_mayor_10":0.0,
        "dias_con_precipitacion_mayor_30":0.0,
        "tension_vapor_media":70,
        "precipitacion_total_mes":1.2,
        "dias_temperatura_menor_0":5,
        "temperatura_media_mes":11.9,
        "indice_evaporacion":1.0,
        "mes":3,
        "year":2023,
        "indice_solar":0.5,
        "sequia_meteorologica":0.0,
        "sequia_agricola":0.0,
        "nomb_estacion":"MUNIESA",
        "provincia":"TERUEL",
        "lat":41.0311111111,
        "long":-0.8055555556
    },
    {
        "id_estacion":"9513X",
        "fecha":"2023-04-01",
        "precipitacion_maxima":"2.8(01)",
        "temperatura_media_minima_mensual":6.9,
        "temperatura_media_maxima_mensual":21.3,
        "temperatura_max_absoluta_mes":"30.8(28)",
        "temperatura_min_absoluta_mes":"-1.1(05)",
        "temperatura_minima_mas_baja":13.2,
        "tempetatura_mas_baja_mes":12.0,
        "dias_con_precipitacion_mayor_01":3.0,
        "dias_con_precipitacion_mayor_0100":2.0,
        "dias_con_precipitacion_mayor_10":0.0,
        "dias_con_precipitacion_mayor_30":0.0,
        "tension_vapor_media":78,
        "precipitacion_total_mes":6.0,
        "dias_temperatura_menor_0":1,
        "temperatura_media_mes":14.2,
        "indice_evaporacion":0.722580173,
        "mes":4,
        "year":2023,
        "indice_solar":0.6,
        "sequia_meteorologica":0.0,
        "sequia_agricola":0.0,
        "nomb_estacion":"MUNIESA",
        "provincia":"TERUEL",
        "lat":41.0311111111,
        "long":-0.8055555556
    },
    {
        "id_estacion":"9513X",
        "fecha":"2023-05-01",
        "precipitacion_maxima":"19.0(24)",
        "temperatura_media_minima_mensual":9.3,
        "temperatura_media_maxima_mensual":21.5,
        "temperatura_max_absoluta_mes":"27.6(03)",
        "temperatura_min_absoluta_mes":"5.6(17)",
        "temperatura_minima_mas_baja":13.5,
        "tempetatura_mas_baja_mes":16.3,
        "dias_con_precipitacion_mayor_01":7.0,
        "dias_con_precipitacion_mayor_0100":6.0,
        "dias_con_precipitacion_mayor_10":1.0,
        "dias_con_precipitacion_mayor_30":0.0,
        "tension_vapor_media":92,
        "precipitacion_total_mes":30.2,
        "dias_temperatura_menor_0":0,
        "temperatura_media_mes":15.4,
        "indice_evaporacion":0.2293239984,
        "mes":5,
        "year":2023,
        "indice_solar":0.7,
        "sequia_meteorologica":0.0713333333,
        "sequia_agricola":0.0623400933,
        "nomb_estacion":"MUNIESA",
        "provincia":"TERUEL",
        "lat":41.0311111111,
        "long":-0.8055555556
    },
    {
        "id_estacion":"9513X",
        "fecha":"2023-06-01",
        "precipitacion_maxima":"25.8(01)",
        "temperatura_media_minima_mensual":14.6,
        "temperatura_media_maxima_mensual":25.9,
        "temperatura_max_absoluta_mes":"33.8(25)",
        "temperatura_min_absoluta_mes":"10.1(02)",
        "temperatura_minima_mas_baja":18.9,
        "tempetatura_mas_baja_mes":16.4,
        "dias_con_precipitacion_mayor_01":15.0,
        "dias_con_precipitacion_mayor_0100":8.0,
        "dias_con_precipitacion_mayor_10":5.0,
        "dias_con_precipitacion_mayor_30":0.0,
        "tension_vapor_media":154,
        "precipitacion_total_mes":100.6,
        "dias_temperatura_menor_0":0,
        "temperatura_media_mes":20.3,
        "indice_evaporacion":0.0,
        "mes":6,
        "year":2023,
        "indice_solar":0.9,
        "sequia_meteorologica":0.7753333333,
        "sequia_agricola":0.7666333333,
        "nomb_estacion":"MUNIESA",
        "provincia":"TERUEL",
        "lat":41.0311111111,
        "long":-0.8055555556
    },
    {
        "id_estacion":"9513X",
        "fecha":"2023-07-01",
        "precipitacion_maxima":"5.0(03)",
        "temperatura_media_minima_mensual":16.8,
        "temperatura_media_maxima_mensual":31.4,
        "temperatura_max_absoluta_mes":"40.1(11)",
        "temperatura_min_absoluta_mes":"11.9(26)",
        "temperatura_minima_mas_baja":24.5,
        "tempetatura_mas_baja_mes":25.1,
        "dias_con_precipitacion_mayor_01":2.0,
        "dias_con_precipitacion_mayor_0100":2.0,
        "dias_con_precipitacion_mayor_10":0.0,
        "dias_con_precipitacion_mayor_30":0.0,
        "tension_vapor_media":160,
        "precipitacion_total_mes":6.4,
        "dias_temperatura_menor_0":0,
        "temperatura_media_mes":24.2,
        "indice_evaporacion":0.8412577994,
        "mes":7,
        "year":2023,
        "indice_solar":1.0,
        "sequia_meteorologica":0.0,
        "sequia_agricola":0.0,
        "nomb_estacion":"MUNIESA",
        "provincia":"TERUEL",
        "lat":41.0311111111,
        "long":-0.8055555556
    },
    {
        "id_estacion":"9513X",
        "fecha":"2023-08-01",
        "precipitacion_maxima":"11.6(13)",
        "temperatura_media_minima_mensual":16.9,
        "temperatura_media_maxima_mensual":31.4,
        "temperatura_max_absoluta_mes":"38.2(24)",
        "temperatura_min_absoluta_mes":"8.9(07)",
        "temperatura_minima_mas_baja":23.2,
        "tempetatura_mas_baja_mes":19.8,
        "dias_con_precipitacion_mayor_01":2.0,
        "dias_con_precipitacion_mayor_0100":2.0,
        "dias_con_precipitacion_mayor_10":1.0,
        "dias_con_precipitacion_mayor_30":0.0,
        "tension_vapor_media":138,
        "precipitacion_total_mes":13.4,
        "dias_temperatura_menor_0":0,
        "temperatura_media_mes":24.2,
        "indice_evaporacion":0.6424262389,
        "mes":8,
        "year":2023,
        "indice_solar":0.9,
        "sequia_meteorologica":0.0,
        "sequia_agricola":0.0,
        "nomb_estacion":"MUNIESA",
        "provincia":"TERUEL",
        "lat":41.0311111111,
        "long":-0.8055555556
    },
    {
        "id_estacion":"9513X",
        "fecha":"2023-09-01",
        "precipitacion_maxima":"17.2(09)",
        "temperatura_media_minima_mensual":14.0,
        "temperatura_media_maxima_mensual":26.1,
        "temperatura_max_absoluta_mes":"31.5(30)",
        "temperatura_min_absoluta_mes":"8.8(23)",
        "temperatura_minima_mas_baja":18.2,
        "tempetatura_mas_baja_mes":19.3,
        "dias_con_precipitacion_mayor_01":7.0,
        "dias_con_precipitacion_mayor_0100":7.0,
        "dias_con_precipitacion_mayor_10":3.0,
        "dias_con_precipitacion_mayor_30":0.0,
        "tension_vapor_media":148,
        "precipitacion_total_mes":47.6,
        "dias_temperatura_menor_0":0,
        "temperatura_media_mes":20.1,
        "indice_evaporacion":0.1741966522,
        "mes":9,
        "year":2023,
        "indice_solar":0.7,
        "sequia_meteorologica":0.2453333333,
        "sequia_agricola":0.2368913668,
        "nomb_estacion":"MUNIESA",
        "provincia":"TERUEL",
        "lat":41.0311111111,
        "long":-0.8055555556
    },
    {
        "id_estacion":"9513X",
        "fecha":"2023-10-01",
        "precipitacion_maxima":"8.0(19)",
        "temperatura_media_minima_mensual":12.2,
        "temperatura_media_maxima_mensual":23.0,
        "temperatura_max_absoluta_mes":"31.9(01)",
        "temperatura_min_absoluta_mes":"6.7(22)",
        "temperatura_minima_mas_baja":17.1,
        "tempetatura_mas_baja_mes":14.9,
        "dias_con_precipitacion_mayor_01":9.0,
        "dias_con_precipitacion_mayor_0100":3.0,
        "dias_con_precipitacion_mayor_10":0.0,
        "dias_con_precipitacion_mayor_30":0.0,
        "tension_vapor_media":113,
        "precipitacion_total_mes":19.6,
        "dias_temperatura_menor_0":0,
        "temperatura_media_mes":17.6,
        "indice_evaporacion":0.4121747166,
        "mes":10,
        "year":2023,
        "indice_solar":0.5,
        "sequia_meteorologica":0.0,
        "sequia_agricola":0.0,
        "nomb_estacion":"MUNIESA",
        "provincia":"TERUEL",
        "lat":41.0311111111,
        "long":-0.8055555556
    },
    {
        "id_estacion":"9513X",
        "fecha":"2023-11-01",
        "precipitacion_maxima":"10.0(02)",
        "temperatura_media_minima_mensual":7.1,
        "temperatura_media_maxima_mensual":16.8,
        "temperatura_max_absoluta_mes":"23.3(13)",
        "temperatura_min_absoluta_mes":"0.9(26)",
        "temperatura_minima_mas_baja":12.9,
        "tempetatura_mas_baja_mes":10.6,
        "dias_con_precipitacion_mayor_01":6.0,
        "dias_con_precipitacion_mayor_0100":3.0,
        "dias_con_precipitacion_mayor_10":1.0,
        "dias_con_precipitacion_mayor_30":0.0,
        "tension_vapor_media":88,
        "precipitacion_total_mes":21.8,
        "dias_temperatura_menor_0":0,
        "temperatura_media_mes":11.9,
        "indice_evaporacion":0.2501162047,
        "mes":11,
        "year":2023,
        "indice_solar":0.3,
        "sequia_meteorologica":0.0,
        "sequia_agricola":0.0,
        "nomb_estacion":"MUNIESA",
        "provincia":"TERUEL",
        "lat":41.0311111111,
        "long":-0.8055555556
    },
    {
        "id_estacion":"9513X",
        "fecha":"2023-12-01",
        "precipitacion_maxima":"3.2(07)",
        "temperatura_media_minima_mensual":3.0,
        "temperatura_media_maxima_mensual":12.5,
        "temperatura_max_absoluta_mes":"19.2(10)",
        "temperatura_min_absoluta_mes":"-1.6(18)",
        "temperatura_minima_mas_baja":10.3,
        "tempetatura_mas_baja_mes":8.1,
        "dias_con_precipitacion_mayor_01":5.0,
        "dias_con_precipitacion_mayor_0100":3.0,
        "dias_con_precipitacion_mayor_10":0.0,
        "dias_con_precipitacion_mayor_30":0.0,
        "tension_vapor_media":68,
        "precipitacion_total_mes":6.6,
        "dias_temperatura_menor_0":6,
        "temperatura_media_mes":7.8,
        "indice_evaporacion":0.5047461753,
        "mes":12,
        "year":2023,
        "indice_solar":0.2,
        "sequia_meteorologica":0.0,
        "sequia_agricola":0.0,
        "nomb_estacion":"MUNIESA",
        "provincia":"TERUEL",
        "lat":41.0311111111,
        "long":-0.8055555556
    },
    {
        "id_estacion":"9513X",
        "fecha":"2024-01-01",
        "precipitacion_maxima":null,
        "temperatura_media_minima_mensual":3.3,
        "temperatura_media_maxima_mensual":12.5,
        "temperatura_max_absoluta_mes":"23.1(25)",
        "temperatura_min_absoluta_mes":"-3.9(12)",
        "temperatura_minima_mas_baja":11.2,
        "tempetatura_mas_baja_mes":2.9,
        "dias_con_precipitacion_mayor_01":null,
        "dias_con_precipitacion_mayor_0100":null,
        "dias_con_precipitacion_mayor_10":null,
        "dias_con_precipitacion_mayor_30":null,
        "tension_vapor_media":74,
        "precipitacion_total_mes":32.6,
        "dias_temperatura_menor_0":8,
        "temperatura_media_mes":7.9,
        "indice_evaporacion":0.1470706186,
        "mes":1,
        "year":2024,
        "indice_solar":0.3,
        "sequia_meteorologica":0.0,
        "sequia_agricola":0.0,
        "nomb_estacion":"MUNIESA",
        "provincia":"TERUEL",
        "lat":41.0311111111,
        "long":-0.8055555556
    },
    {
        "id_estacion":"9513X",
        "fecha":"2024-02-01",
        "precipitacion_maxima":"8.0(15)",
        "temperatura_media_minima_mensual":4.4,
        "temperatura_media_maxima_mensual":14.2,
        "temperatura_max_absoluta_mes":"18.7(13)",
        "temperatura_min_absoluta_mes":"1.8(03)",
        "temperatura_minima_mas_baja":8.3,
        "tempetatura_mas_baja_mes":7.3,
        "dias_con_precipitacion_mayor_01":10.0,
        "dias_con_precipitacion_mayor_0100":3.0,
        "dias_con_precipitacion_mayor_10":0.0,
        "dias_con_precipitacion_mayor_30":0.0,
        "tension_vapor_media":72,
        "precipitacion_total_mes":18.4,
        "dias_temperatura_menor_0":0,
        "temperatura_media_mes":9.3,
        "indice_evaporacion":0.3759533149,
        "mes":2,
        "year":2024,
        "indice_solar":0.4,
        "sequia_meteorologica":0.0,
        "sequia_agricola":0.0,
        "nomb_estacion":"MUNIESA",
        "provincia":"TERUEL",
        "lat":41.0311111111,
        "long":-0.8055555556
    },
    {
        "id_estacion":"9513X",
        "fecha":"2024-03-01",
        "precipitacion_maxima":"8.0(25)",
        "temperatura_media_minima_mensual":5.1,
        "temperatura_media_maxima_mensual":16.2,
        "temperatura_max_absoluta_mes":"25.3(22)",
        "temperatura_min_absoluta_mes":"0.8(01)",
        "temperatura_minima_mas_baja":10.3,
        "tempetatura_mas_baja_mes":7.8,
        "dias_con_precipitacion_mayor_01":10.0,
        "dias_con_precipitacion_mayor_0100":7.0,
        "dias_con_precipitacion_mayor_10":0.0,
        "dias_con_precipitacion_mayor_30":0.0,
        "tension_vapor_media":78,
        "precipitacion_total_mes":23.8,
        "dias_temperatura_menor_0":0,
        "temperatura_media_mes":10.7,
        "indice_evaporacion":0.3343102202,
        "mes":3,
        "year":2024,
        "indice_solar":0.5,
        "sequia_meteorologica":0.0,
        "sequia_agricola":0.0,
        "nomb_estacion":"MUNIESA",
        "provincia":"TERUEL",
        "lat":41.0311111111,
        "long":-0.8055555556
    },
    {
        "id_estacion":"9513X",
        "fecha":"2024-04-01",
        "precipitacion_maxima":"15.0(28)",
        "temperatura_media_minima_mensual":6.4,
        "temperatura_media_maxima_mensual":19.2,
        "temperatura_max_absoluta_mes":"28.9(06)",
        "temperatura_min_absoluta_mes":"0.7(19)",
        "temperatura_minima_mas_baja":15.2,
        "tempetatura_mas_baja_mes":11.5,
        "dias_con_precipitacion_mayor_01":3.0,
        "dias_con_precipitacion_mayor_0100":2.0,
        "dias_con_precipitacion_mayor_10":1.0,
        "dias_con_precipitacion_mayor_30":0.0,
        "tension_vapor_media":71,
        "precipitacion_total_mes":16.8,
        "dias_temperatura_menor_0":0,
        "temperatura_media_mes":12.8,
        "indice_evaporacion":0.5332711602,
        "mes":4,
        "year":2024,
        "indice_solar":0.6,
        "sequia_meteorologica":0.0,
        "sequia_agricola":0.0,
        "nomb_estacion":"MUNIESA",
        "provincia":"TERUEL",
        "lat":41.0311111111,
        "long":-0.8055555556
    },
    {
        "id_estacion":"9513X",
        "fecha":"2024-05-01",
        "precipitacion_maxima":"16.8(19)",
        "temperatura_media_minima_mensual":9.0,
        "temperatura_media_maxima_mensual":21.9,
        "temperatura_max_absoluta_mes":"29.2(29)",
        "temperatura_min_absoluta_mes":"3.5(02)",
        "temperatura_minima_mas_baja":14.0,
        "tempetatura_mas_baja_mes":14.2,
        "dias_con_precipitacion_mayor_01":8.0,
        "dias_con_precipitacion_mayor_0100":3.0,
        "dias_con_precipitacion_mayor_10":1.0,
        "dias_con_precipitacion_mayor_30":0.0,
        "tension_vapor_media":95,
        "precipitacion_total_mes":25.6,
        "dias_temperatura_menor_0":0,
        "temperatura_media_mes":15.5,
        "indice_evaporacion":0.443292823,
        "mes":5,
        "year":2024,
        "indice_solar":0.7,
        "sequia_meteorologica":0.0,
        "sequia_agricola":0.0,
        "nomb_estacion":"MUNIESA",
        "provincia":"TERUEL",
        "lat":41.0311111111,
        "long":-0.8055555556
    },
    {
        "id_estacion":"9513X",
        "fecha":"2024-06-01",
        "precipitacion_maxima":"26.2(08)",
        "temperatura_media_minima_mensual":13.5,
        "temperatura_media_maxima_mensual":26.3,
        "temperatura_max_absoluta_mes":"34.8(06)",
        "temperatura_min_absoluta_mes":"7.5(13)",
        "temperatura_minima_mas_baja":19.9,
        "tempetatura_mas_baja_mes":17.9,
        "dias_con_precipitacion_mayor_01":6.0,
        "dias_con_precipitacion_mayor_0100":5.0,
        "dias_con_precipitacion_mayor_10":2.0,
        "dias_con_precipitacion_mayor_30":0.0,
        "tension_vapor_media":124,
        "precipitacion_total_mes":51.6,
        "dias_temperatura_menor_0":0,
        "temperatura_media_mes":19.9,
        "indice_evaporacion":0.282534069,
        "mes":6,
        "year":2024,
        "indice_solar":0.9,
        "sequia_meteorologica":0.1138333333,
        "sequia_agricola":0.1023079926,
        "nomb_estacion":"MUNIESA",
        "provincia":"TERUEL",
        "lat":41.0311111111,
        "long":-0.8055555556
    },
    {
        "id_estacion":"9513X",
        "fecha":"2024-07-01",
        "precipitacion_maxima":"5.0(29)",
        "temperatura_media_minima_mensual":17.4,
        "temperatura_media_maxima_mensual":31.8,
        "temperatura_max_absoluta_mes":"38.5(31)",
        "temperatura_min_absoluta_mes":"10.8(22)",
        "temperatura_minima_mas_baja":25.4,
        "tempetatura_mas_baja_mes":23.7,
        "dias_con_precipitacion_mayor_01":3.0,
        "dias_con_precipitacion_mayor_0100":2.0,
        "dias_con_precipitacion_mayor_10":0.0,
        "dias_con_precipitacion_mayor_30":0.0,
        "tension_vapor_media":140,
        "precipitacion_total_mes":9.6,
        "dias_temperatura_menor_0":0,
        "temperatura_media_mes":24.6,
        "indice_evaporacion":1.0,
        "mes":7,
        "year":2024,
        "indice_solar":1.0,
        "sequia_meteorologica":0.0,
        "sequia_agricola":0.0,
        "nomb_estacion":"MUNIESA",
        "provincia":"TERUEL",
        "lat":41.0311111111,
        "long":-0.8055555556
    },
    {
        "id_estacion":"9513X",
        "fecha":"2024-08-01",
        "precipitacion_maxima":"48.8(29)",
        "temperatura_media_minima_mensual":17.1,
        "temperatura_media_maxima_mensual":31.3,
        "temperatura_max_absoluta_mes":"37.1(11)",
        "temperatura_min_absoluta_mes":"11.4(19)",
        "temperatura_minima_mas_baja":21.1,
        "tempetatura_mas_baja_mes":22.6,
        "dias_con_precipitacion_mayor_01":6.0,
        "dias_con_precipitacion_mayor_0100":4.0,
        "dias_con_precipitacion_mayor_10":3.0,
        "dias_con_precipitacion_mayor_30":2.0,
        "tension_vapor_media":152,
        "precipitacion_total_mes":111.4,
        "dias_temperatura_menor_0":0,
        "temperatura_media_mes":24.2,
        "indice_evaporacion":0.1200696506,
        "mes":8,
        "year":2024,
        "indice_solar":0.9,
        "sequia_meteorologica":0.7118333333,
        "sequia_agricola":0.7019326368,
        "nomb_estacion":"MUNIESA",
        "provincia":"TERUEL",
        "lat":41.0311111111,
        "long":-0.8055555556
    },
    {
        "id_estacion":"9513X",
        "fecha":"2024-09-01",
        "precipitacion_maxima":"21.8(21)",
        "temperatura_media_minima_mensual":11.7,
        "temperatura_media_maxima_mensual":22.0,
        "temperatura_max_absoluta_mes":"27.3(07)",
        "temperatura_min_absoluta_mes":"5.0(14)",
        "temperatura_minima_mas_baja":17.2,
        "tempetatura_mas_baja_mes":16.7,
        "dias_con_precipitacion_mayor_01":7.0,
        "dias_con_precipitacion_mayor_0100":6.0,
        "dias_con_precipitacion_mayor_10":1.0,
        "dias_con_precipitacion_mayor_30":0.0,
        "tension_vapor_media":127,
        "precipitacion_total_mes":43.8,
        "dias_temperatura_menor_0":0,
        "temperatura_media_mes":16.9,
        "indice_evaporacion":0.2826915069,
        "mes":9,
        "year":2024,
        "indice_solar":0.7,
        "sequia_meteorologica":0.0358333333,
        "sequia_agricola":0.0263064183,
        "nomb_estacion":"MUNIESA",
        "provincia":"TERUEL",
        "lat":41.0311111111,
        "long":-0.8055555556
    },
    {
        "id_estacion":"9513X",
        "fecha":"2024-10-01",
        "precipitacion_maxima":"28.8(29)",
        "temperatura_media_minima_mensual":10.7,
        "temperatura_media_maxima_mensual":18.9,
        "temperatura_max_absoluta_mes":"26.6(07)",
        "temperatura_min_absoluta_mes":"5.7(27)",
        "temperatura_minima_mas_baja":17.4,
        "tempetatura_mas_baja_mes":8.4,
        "dias_con_precipitacion_mayor_01":14.0,
        "dias_con_precipitacion_mayor_0100":11.0,
        "dias_con_precipitacion_mayor_10":6.0,
        "dias_con_precipitacion_mayor_30":0.0,
        "tension_vapor_media":127,
        "precipitacion_total_mes":126.6,
        "dias_temperatura_menor_0":0,
        "temperatura_media_mes":14.8,
        "indice_evaporacion":0.0,
        "mes":10,
        "year":2024,
        "indice_solar":0.5,
        "sequia_meteorologica":0.8638333333,
        "sequia_agricola":0.8591333333,
        "nomb_estacion":"MUNIESA",
        "provincia":"TERUEL",
        "lat":41.0311111111,
        "long":-0.8055555556
    },
    {
        "id_estacion":"9513X",
        "fecha":"2024-11-01",
        "precipitacion_maxima":"5.8(13)",
        "temperatura_media_minima_mensual":6.7,
        "temperatura_media_maxima_mensual":15.6,
        "temperatura_max_absoluta_mes":"20.6(25)",
        "temperatura_min_absoluta_mes":"1.9(22)",
        "temperatura_minima_mas_baja":11.0,
        "tempetatura_mas_baja_mes":7.0,
        "dias_con_precipitacion_mayor_01":8.0,
        "dias_con_precipitacion_mayor_0100":5.0,
        "dias_con_precipitacion_mayor_10":0.0,
        "dias_con_precipitacion_mayor_30":0.0,
        "tension_vapor_media":107,
        "precipitacion_total_mes":15.8,
        "dias_temperatura_menor_0":0,
        "temperatura_media_mes":11.2,
        "indice_evaporacion":0.5046073905,
        "mes":11,
        "year":2024,
        "indice_solar":0.3,
        "sequia_meteorologica":0.0,
        "sequia_agricola":0.0,
        "nomb_estacion":"MUNIESA",
        "provincia":"TERUEL",
        "lat":41.0311111111,
        "long":-0.8055555556
    },
    {
        "id_estacion":"9513X",
        "fecha":"2024-12-01",
        "precipitacion_maxima":"1.6(11)",
        "temperatura_media_minima_mensual":2.1,
        "temperatura_media_maxima_mensual":10.7,
        "temperatura_max_absoluta_mes":"19.2(01)",
        "temperatura_min_absoluta_mes":"-5.3(31)",
        "temperatura_minima_mas_baja":7.9,
        "tempetatura_mas_baja_mes":3.3,
        "dias_con_precipitacion_mayor_01":8.0,
        "dias_con_precipitacion_mayor_0100":3.0,
        "dias_con_precipitacion_mayor_10":0.0,
        "dias_con_precipitacion_mayor_30":0.0,
        "tension_vapor_media":74,
        "precipitacion_total_mes":6.6,
        "dias_temperatura_menor_0":7,
        "temperatura_media_mes":6.4,
        "indice_evaporacion":0.6306874677,
        "mes":12,
        "year":2024,
        "indice_solar":0.2,
        "sequia_meteorologica":0.0,
        "sequia_agricola":0.0,
        "nomb_estacion":"MUNIESA",
        "provincia":"TERUEL",
        "lat":41.0311111111,
        "long":-0.8055555556
    }
]