[
    {
        "fecha": "2023-10",
        "indicativo": "5103F",
        "n_cub": "4",
        "hr": "48",
        "q_max": "859.1(04)",
        "nw_55": "11",
        "q_mar": "1014.7",
        "q_med": "849.2",
        "tm_min": "10.4",
        "ta_max": "28.8(03)",
        "ts_min": "15.8",
        "nt_30": "0",
        "n_des": "9",
        "w_racha": "26/26.1(19)",
        "n_nub": "18",
        "nw_91": "2",
        "ta_min": "4.5(31)",
        "w_rec": "275",
        "e": "77",
        "w_med": "11",
        "nt_00": "0",
        "ti_max": "9.6",
        "tm_mes": "15.7",
        "tm_max": "21.0",
        "q_min": "830.1(19)"
    },
    {
        "fecha": "2023-11",
        "indicativo": "5103F",
        "n_cub": "1",
        "hr": "48",
        "q_max": "858.3(14)",
        "nw_55": "7",
        "q_mar": "1018.1",
        "q_med": "849.7",
        "tm_min": "6.1",
        "ta_max": "22.1(11)",
        "ts_min": "11.9",
        "nt_30": "0",
        "n_des": "15",
        "w_racha": "23/26.9(02)",
        "n_nub": "14",
        "nw_91": "2",
        "ta_min": "-0.9(22)",
        "w_rec": "269",
        "e": "63",
        "w_med": "12",
        "nt_00": "1",
        "ti_max": "7.9",
        "tm_mes": "11.2",
        "tm_max": "16.3",
        "q_min": "837.0(30)"
    },
    {
        "fecha": "2023-12",
        "indicativo": "5103F",
        "n_cub": "6",
        "hr": "45",
        "q_max": "861.3(16)",
        "nw_55": "4",
        "q_mar": "1023.0",
        "q_med": "852.0",
        "tm_min": "3.3",
        "ta_max": "22.4(11)",
        "ts_min": "13.1",
        "nt_30": "0",
        "n_des": "17",
        "w_racha": "24/23.1(01)",
        "n_nub": "8",
        "nw_91": "0",
        "ta_min": "-1.8(03)",
        "w_rec": "189",
        "e": "48",
        "w_med": "8",
        "nt_00": "7",
        "ti_max": "7.4",
        "tm_mes": "7.9",
        "tm_max": "12.5",
        "q_min": "834.5(01)"
    },
    {
        "fecha": "2023-13",
        "indicativo": "5103F"
    },
    {
        "fecha": "2023-1",
        "indicativo": "5103F"
    },
    {
        "fecha": "2023-2",
        "indicativo": "5103F"
    },
    {
        "fecha": "2023-3",
        "indicativo": "5103F"
    },
    {
        "fecha": "2023-4",
        "indicativo": "5103F"
    },
    {
        "fecha": "2023-5",
        "indicativo": "5103F"
    },
    {
        "fecha": "2023-6",
        "indicativo": "5103F"
    },
    {
        "fecha": "2023-7",
        "indicativo": "5103F"
    },
    {
        "fecha": "2023-8",
        "indicativo": "5103F",
        "n_cub": "0",
        "hr": "23",
        "q_max": "858.1(10)",
        "nw_55": "1",
        "q_mar": "1011.5",
        "q_med": "852.1",
        "tm_min": "18.5",
        "ta_max": "39.6(09)",
        "ts_min": "24.6",
        "nt_30": "25",
        "n_des": "20",
        "w_racha": "24/15.8(27)",
        "n_nub": "11",
        "nw_91": "0",
        "ta_min": "10.0(28)",
        "w_rec": "232",
        "e": "77",
        "w_med": "7",
        "nt_00": "0",
        "ti_max": "22.6",
        "tm_mes": "25.7",
        "tm_max": "33.0",
        "q_min": "845.0(27)"
    },
    {
        "fecha": "2023-9",
        "indicativo": "5103F",
        "n_cub": "4",
        "hr": "51",
        "q_max": "858.1(30)",
        "nw_55": "1",
        "q_mar": "1013.5",
        "q_med": "850.2",
        "tm_min": "12.7",
        "ta_max": "29.1(29)",
        "ts_min": "16.6",
        "nt_30": "0",
        "n_des": "9",
        "w_racha": "26/15.3(21)",
        "n_nub": "17",
        "nw_91": "0",
        "ta_min": "8.2(23)",
        "w_rec": "181",
        "e": "107",
        "w_med": "7",
        "nt_00": "0",
        "ti_max": "17.3",
        "tm_mes": "18.8",
        "tm_max": "24.9",
        "q_min": "842.0(03)"
    }
]