[
    {
        "fecha": "2021-10",
        "indicativo": "2044B",
        "p_max": "18.8(29)",
        "n_cub": "5",
        "hr": "63",
        "nw_55": "1",
        "tm_min": "4.0",
        "ta_max": "25.3(07)",
        "ts_min": "9.5",
        "nt_30": "0",
        "n_des": "13",
        "w_racha": "27/15.3(31)",
        "np_100": "3",
        "n_nub": "13",
        "nw_91": "0",
        "np_001": "7",
        "ta_min": "-1.8(24)",
        "w_rec": "216",
        "e": "87",
        "np_300": "0",
        "p_mes": "49.0",
        "w_med": "10",
        "nt_00": "2",
        "ti_max": "11.9",
        "tm_mes": "11.9",
        "tm_max": "19.8",
        "np_010": "5"
    },
    {
        "fecha": "2021-11",
        "indicativo": "2044B",
        "p_max": "18.0(22)",
        "n_cub": "7",
        "hr": "78",
        "nw_55": "6",
        "tm_min": "-0.8",
        "ta_max": "17.8(12)",
        "ts_min": "5.3",
        "nt_30": "0",
        "n_des": "11",
        "w_racha": "28/17.2(29)",
        "np_100": "3",
        "n_nub": "12",
        "nw_91": "0",
        "np_001": "8",
        "ta_min": "-3.8(18)",
        "w_rec": "274",
        "e": "64",
        "np_300": "0",
        "p_mes": "57.8",
        "w_med": "12",
        "nt_00": "25",
        "ti_max": "2.3",
        "tm_mes": "4.8",
        "tm_max": "10.4",
        "np_010": "8"
    },
    {
        "fecha": "2021-12",
        "indicativo": "2044B",
        "p_max": "10.0(26)",
        "n_cub": "4",
        "hr": "81",
        "nw_55": "8",
        "tm_min": "1.0",
        "ta_max": "20.6(31)",
        "ts_min": "6.7",
        "nt_30": "0",
        "n_des": "7",
        "w_racha": "99/17.8(09)",
        "np_100": "1",
        "n_nub": "19",
        "nw_91": "0",
        "np_001": "11",
        "ta_min": "-3.3(18)",
        "w_rec": "317",
        "e": "75",
        "np_300": "0",
        "p_mes": "31.0",
        "w_med": "14",
        "nt_00": "16",
        "ti_max": "4.1",
        "tm_mes": "5.9",
        "tm_max": "10.8",
        "np_010": "6"
    },
    {
        "fecha": "2021-13",
        "indicativo": "2044B"
    },
    {
        "fecha": "2021-1",
        "indicativo": "2044B",
        "p_max": "20.2(23)",
        "hr": "85",
        "nw_55": "8",
        "tm_min": "-3.5",
        "ta_max": "16.1(28)",
        "ts_min": "7.8",
        "nt_30": "0",
        "w_racha": "26/24.7(22)",
        "np_100": "2",
        "nw_91": "0",
        "np_001": "15",
        "ta_min": "-14.3(11)",
        "w_rec": "373",
        "e": "61",
        "np_300": "0",
        "p_mes": "89.2",
        "w_med": "16",
        "nt_00": "20",
        "ti_max": "-3.2",
        "tm_mes": "1.2",
        "tm_max": "6.0",
        "np_010": "11"
    },
    {
        "fecha": "2021-2",
        "indicativo": "2044B",
        "p_max": "18.2(09)",
        "hr": "80",
        "nw_55": "4",
        "tm_min": "1.4",
        "ta_max": "16.9(27)",
        "ts_min": "6.3",
        "nt_30": "0",
        "w_racha": "25/20.3(01)",
        "np_100": "2",
        "nw_91": "0",
        "np_001": "12",
        "ta_min": "-3.0(07)",
        "w_rec": "306",
        "e": "76",
        "np_300": "0",
        "p_mes": "61.2",
        "w_med": "14",
        "nt_00": "11",
        "ti_max": "4.9",
        "tm_mes": "6.6",
        "tm_max": "11.8",
        "np_010": "11"
    },
    {
        "fecha": "2021-3",
        "indicativo": "2044B",
        "p_max": "2.8(07)",
        "hr": "60",
        "nw_55": "3",
        "tm_min": "0.2",
        "ta_max": "23.1(31)",
        "ts_min": "4.1",
        "nt_30": "0",
        "w_racha": "02/17.8(17)",
        "np_100": "0",
        "nw_91": "0",
        "np_001": "3",
        "ta_min": "-5.1(10)",
        "w_rec": "290",
        "e": "60",
        "np_300": "0",
        "p_mes": "3.4",
        "w_med": "13",
        "nt_00": "12",
        "ti_max": "6.1",
        "tm_mes": "6.9",
        "tm_max": "13.5",
        "np_010": "1"
    },
    {
        "fecha": "2021-4",
        "indicativo": "2044B",
        "p_max": "12.4(10)",
        "nw_55": "0",
        "tm_min": "2.6",
        "ta_max": "21.6(01)",
        "ts_min": "7.7",
        "nt_30": "0",
        "w_racha": "26/13.6(20)",
        "np_100": "1",
        "nw_91": "0",
        "np_001": "15",
        "ta_min": "-2.7(07)",
        "w_rec": "246",
        "e": "73",
        "np_300": "0",
        "p_mes": "53.8",
        "w_med": "11",
        "nt_00": "10",
        "ti_max": "9.0",
        "tm_mes": "8.9",
        "tm_max": "15.4",
        "np_010": "12"
    },
    {
        "fecha": "2021-5",
        "indicativo": "2044B",
        "p_max": "14.4(13)",
        "tm_min": "5.3",
        "ta_max": "28.1(29)",
        "ts_min": "11.8",
        "nt_30": "0",
        "np_100": "1",
        "np_001": "9",
        "ta_min": "-0.2(04)",
        "np_300": "0",
        "p_mes": "46.0",
        "nt_00": "1",
        "ti_max": "9.6",
        "tm_mes": "12.2",
        "tm_max": "19.0",
        "np_010": "8"
    },
    {
        "fecha": "2021-6",
        "indicativo": "2044B"
    },
    {
        "fecha": "2021-7",
        "indicativo": "2044B",
        "p_max": "3.2(31)",
        "hr": "41",
        "nw_55": "3",
        "tm_min": "10.4",
        "ta_max": "35.4(11)",
        "ts_min": "15.1",
        "nt_30": "14",
        "w_racha": "24/17.5(29)",
        "np_100": "0",
        "nw_91": "0",
        "np_001": "5",
        "ta_min": "3.4(13)",
        "w_rec": "253",
        "e": "106",
        "np_300": "0",
        "p_mes": "7.4",
        "w_med": "12",
        "nt_00": "0",
        "ti_max": "17.9",
        "tm_mes": "19.4",
        "tm_max": "28.4",
        "np_010": "3"
    },
    {
        "fecha": "2021-8",
        "indicativo": "2044B",
        "p_max": "6.8(11)",
        "hr": "37",
        "nw_55": "3",
        "tm_min": "11.1",
        "ta_max": "38.6(14)",
        "ts_min": "16.9",
        "nt_30": "18",
        "w_racha": "20/18.9(11)",
        "np_100": "0",
        "nw_91": "0",
        "np_001": "3",
        "ta_min": "4.3(01)",
        "w_rec": "250",
        "e": "102",
        "np_300": "0",
        "p_mes": "11.0",
        "w_med": "12",
        "nt_00": "0",
        "ti_max": "22.2",
        "tm_mes": "21.0",
        "tm_max": "30.8",
        "np_010": "2"
    },
    {
        "fecha": "2021-9",
        "indicativo": "2044B",
        "p_max": "33.8(24)",
        "hr": "62",
        "nw_55": "0",
        "tm_min": "9.8",
        "ta_max": "29.6(05)",
        "ts_min": "14.2",
        "nt_30": "0",
        "w_racha": "21/12.5(13)",
        "np_100": "2",
        "nw_91": "0",
        "np_001": "9",
        "ta_min": "3.9(19)",
        "w_rec": "227",
        "e": "119",
        "np_300": "1",
        "p_mes": "78.6",
        "w_med": "9",
        "nt_00": "0",
        "ti_max": "17.5",
        "tm_mes": "16.6",
        "tm_max": "23.4",
        "np_010": "6"
    }
]